{"content":"\"{\\\"object\\\":\\\"value\\\",\\\"document\\\":{\\\"object\\\":\\\"document\\\",\\\"data\\\":{},\\\"nodes\\\":[{\\\"object\\\":\\\"block\\\",\\\"type\\\":\\\"paragraph\\\",\\\"data\\\":{},\\\"nodes\\\":[{\\\"object\\\":\\\"text\\\",\\\"text\\\":\\\"You can download the VS installs from EPAM SAM. \\\",\\\"marks\\\":[{\\\"object\\\":\\\"mark\\\",\\\"type\\\":\\\"uui-richTextEditor-span-mark\\\",\\\"data\\\":{\\\"style\\\":{}}}]},{\\\"object\\\":\\\"text\\\",\\\"text\\\":\\\"You must be in the office to access this, or have active EPAM GlobalProtect VPN, while SLB PulseSecure VPN disconnected.\\\",\\\"marks\\\":[{\\\"object\\\":\\\"mark\\\",\\\"type\\\":\\\"uui-richTextEditor-span-mark\\\",\\\"data\\\":{\\\"style\\\":{}}}]}]},{\\\"object\\\":\\\"block\\\",\\\"type\\\":\\\"note-link\\\",\\\"data\\\":{},\\\"nodes\\\":[{\\\"object\\\":\\\"text\\\",\\\"text\\\":\\\" \\\\\\\\\\\\\\\\epam.com\\\\\\\\SAM\\\\\\\\Softarchive\\\\\\\\Dot_Net_Developer_with_VS \\\",\\\"marks\\\":[{\\\"object\\\":\\\"mark\\\",\\\"type\\\":\\\"uui-richTextEditor-span-mark\\\",\\\"data\\\":{\\\"style\\\":{}}}]}]},{\\\"object\\\":\\\"block\\\",\\\"type\\\":\\\"paragraph\\\",\\\"data\\\":{},\\\"nodes\\\":[{\\\"object\\\":\\\"text\\\",\\\"text\\\":\\\"If you're a developer, you should be able to access the developer software package in the shared drive.\\\",\\\"marks\\\":[]}]},{\\\"object\\\":\\\"block\\\",\\\"type\\\":\\\"paragraph\\\",\\\"data\\\":{},\\\"nodes\\\":[{\\\"object\\\":\\\"text\\\",\\\"text\\\":\\\"\\\",\\\"marks\\\":[{\\\"object\\\":\\\"mark\\\",\\\"type\\\":\\\"uui-richTextEditor-span-mark\\\",\\\"data\\\":{\\\"style\\\":{}}}]}]},{\\\"object\\\":\\\"block\\\",\\\"type\\\":\\\"uui-richTextEditor-header-2\\\",\\\"data\\\":{},\\\"nodes\\\":[{\\\"object\\\":\\\"text\\\",\\\"text\\\":\\\"Visual Studio Install 2019 on Windows 10\\\",\\\"marks\\\":[{\\\"object\\\":\\\"mark\\\",\\\"type\\\":\\\"uui-richTextEditor-span-mark\\\",\\\"data\\\":{\\\"style\\\":{\\\"color\\\":\\\"#669900\\\"}}}]}]},{\\\"object\\\":\\\"block\\\",\\\"type\\\":\\\"uui-richTextEditor-header-3\\\",\\\"data\\\":{},\\\"nodes\\\":[{\\\"object\\\":\\\"text\\\",\\\"text\\\":\\\"Some parts here are deprecated:\\\",\\\"marks\\\":[{\\\"object\\\":\\\"mark\\\",\\\"type\\\":\\\"uui-richTextEditor-span-mark\\\",\\\"data\\\":{\\\"style\\\":{}}}]}]},{\\\"object\\\":\\\"block\\\",\\\"type\\\":\\\"unordered-list\\\",\\\"data\\\":{},\\\"nodes\\\":[{\\\"object\\\":\\\"block\\\",\\\"type\\\":\\\"list-item\\\",\\\"data\\\":{},\\\"nodes\\\":[{\\\"object\\\":\\\"block\\\",\\\"type\\\":\\\"list-item-child\\\",\\\"data\\\":{},\\\"nodes\\\":[{\\\"object\\\":\\\"text\\\",\\\"text\\\":\\\"- VS 2013 uninstall (if present)\\\",\\\"marks\\\":[]}]}]},{\\\"object\\\":\\\"block\\\",\\\"type\\\":\\\"list-item\\\",\\\"data\\\":{},\\\"nodes\\\":[{\\\"object\\\":\\\"block\\\",\\\"type\\\":\\\"list-item-child\\\",\\\"data\\\":{},\\\"nodes\\\":[{\\\"object\\\":\\\"text\\\",\\\"text\\\":\\\".NET 4.5.1 uninstall (if present)\\\",\\\"marks\\\":[]}]}]},{\\\"object\\\":\\\"block\\\",\\\"type\\\":\\\"list-item\\\",\\\"data\\\":{},\\\"nodes\\\":[{\\\"object\\\":\\\"block\\\",\\\"type\\\":\\\"list-item-child\\\",\\\"data\\\":{},\\\"nodes\\\":[{\\\"object\\\":\\\"text\\\",\\\"text\\\":\\\" .NET 4.5 install (IMPORTANT, install 4.5, NOT 4.5.1!)\\\",\\\"marks\\\":[]}]}]},{\\\"object\\\":\\\"block\\\",\\\"type\\\":\\\"list-item\\\",\\\"data\\\":{},\\\"nodes\\\":[{\\\"object\\\":\\\"block\\\",\\\"type\\\":\\\"list-item-child\\\",\\\"data\\\":{},\\\"nodes\\\":[{\\\"object\\\":\\\"text\\\",\\\"text\\\":\\\" install .NET hotfix (\\\\\\\\\\\\\\\\EPHUBUDW0190\\\\\\\\TeamShare\\\\\\\\SLB_TEAM_SHARE\\\\\\\\RampUp\\\\\\\\NDP45-KB2848798-x64.zip)\\\",\\\"marks\\\":[]}]}]},{\\\"object\\\":\\\"block\\\",\\\"type\\\":\\\"list-item\\\",\\\"data\\\":{},\\\"nodes\\\":[{\\\"object\\\":\\\"block\\\",\\\"type\\\":\\\"list-item-child\\\",\\\"data\\\":{},\\\"nodes\\\":[{\\\"object\\\":\\\"text\\\",\\\"text\\\":\\\"VS 2012 + SPs (yes, you need VS2012 for it's compiler binaries)\\\",\\\"marks\\\":[]}]}]},{\\\"object\\\":\\\"block\\\",\\\"type\\\":\\\"list-item\\\",\\\"data\\\":{},\\\"nodes\\\":[{\\\"object\\\":\\\"block\\\",\\\"type\\\":\\\"list-item-child\\\",\\\"data\\\":{},\\\"nodes\\\":[{\\\"object\\\":\\\"text\\\",\\\"text\\\":\\\"VS 2013 + update 2-5\\\",\\\"marks\\\":[]}]}]}]},{\\\"object\\\":\\\"block\\\",\\\"type\\\":\\\"paragraph\\\",\\\"data\\\":{},\\\"nodes\\\":[{\\\"object\\\":\\\"text\\\",\\\"text\\\":\\\"\\\",\\\"marks\\\":[]}]},{\\\"object\\\":\\\"block\\\",\\\"type\\\":\\\"uui-richTextEditor-header-3\\\",\\\"data\\\":{},\\\"nodes\\\":[{\\\"object\\\":\\\"text\\\",\\\"text\\\":\\\"Install Perforce client\\\",\\\"marks\\\":[{\\\"object\\\":\\\"mark\\\",\\\"type\\\":\\\"uui-richTextEditor-span-mark\\\",\\\"data\\\":{\\\"style\\\":{\\\"color\\\":\\\"rgb(70, 69, 71)\\\"}}}]}]},{\\\"object\\\":\\\"block\\\",\\\"type\\\":\\\"paragraph\\\",\\\"data\\\":{},\\\"nodes\\\":[{\\\"object\\\":\\\"text\\\",\\\"text\\\":\\\"Download the latest Perforce Client (p4v) which is free at the moment.\\\",\\\"marks\\\":[]}]},{\\\"object\\\":\\\"block\\\",\\\"type\\\":\\\"paragraph\\\",\\\"data\\\":{},\\\"nodes\\\":[{\\\"object\\\":\\\"text\\\",\\\"text\\\":\\\"You can find the latest package\\\",\\\"marks\\\":[]},{\\\"object\\\":\\\"inline\\\",\\\"type\\\":\\\"link\\\",\\\"data\\\":{\\\"url\\\":\\\"http://www.perforce.com/downloads/helix#product-9\\\"},\\\"nodes\\\":[{\\\"object\\\":\\\"text\\\",\\\"text\\\":\\\" here\\\",\\\"marks\\\":[{\\\"object\\\":\\\"mark\\\",\\\"type\\\":\\\"uui-richTextEditor-bold\\\",\\\"data\\\":{}}]}]},{\\\"object\\\":\\\"text\\\",\\\"text\\\":\\\".\\\",\\\"marks\\\":[{\\\"object\\\":\\\"mark\\\",\\\"type\\\":\\\"uui-richTextEditor-bold\\\",\\\"data\\\":{}}]}]},{\\\"object\\\":\\\"block\\\",\\\"type\\\":\\\"uui-richTextEditor-header-3\\\",\\\"data\\\":{},\\\"nodes\\\":[{\\\"object\\\":\\\"text\\\",\\\"text\\\":\\\"\\\",\\\"marks\\\":[]}]},{\\\"object\\\":\\\"block\\\",\\\"type\\\":\\\"uui-richTextEditor-header-3\\\",\\\"data\\\":{},\\\"nodes\\\":[{\\\"object\\\":\\\"text\\\",\\\"text\\\":\\\"Configuring Perforce Client\\\",\\\"marks\\\":[]}]},{\\\"object\\\":\\\"block\\\",\\\"type\\\":\\\"paragraph\\\",\\\"data\\\":{},\\\"nodes\\\":[{\\\"object\\\":\\\"text\\\",\\\"text\\\":\\\"Run P4V and skip connection wizard use Connection -> Open connection instead.\\\",\\\"marks\\\":[]}]},{\\\"object\\\":\\\"block\\\",\\\"type\\\":\\\"paragraph\\\",\\\"data\\\":{},\\\"nodes\\\":[{\\\"object\\\":\\\"text\\\",\\\"text\\\":\\\"Note: You have to be connected to the secure gateway while you use Perforce Client!\\\",\\\"marks\\\":[]}]},{\\\"object\\\":\\\"block\\\",\\\"type\\\":\\\"unordered-list\\\",\\\"data\\\":{},\\\"nodes\\\":[{\\\"object\\\":\\\"block\\\",\\\"type\\\":\\\"list-item\\\",\\\"data\\\":{},\\\"nodes\\\":[{\\\"object\\\":\\\"block\\\",\\\"type\\\":\\\"list-item-child\\\",\\\"data\\\":{},\\\"nodes\\\":[{\\\"object\\\":\\\"text\\\",\\\"text\\\":\\\"Server:\\\",\\\"marks\\\":[]},{\\\"object\\\":\\\"text\\\",\\\"text\\\":\\\" \\\",\\\"marks\\\":[{\\\"object\\\":\\\"mark\\\",\\\"type\\\":\\\"uui-richTextEditor-span-mark\\\",\\\"data\\\":{\\\"style\\\":{}}},{\\\"object\\\":\\\"mark\\\",\\\"type\\\":\\\"uui-richTextEditor-bold\\\",\\\"data\\\":{}}]},{\\\"object\\\":\\\"inline\\\",\\\"type\\\":\\\"link\\\",\\\"data\\\":{\\\"url\\\":\\\"https://kb.epam.com/display/SLBOCT/Useful+links\\\"},\\\"nodes\\\":[{\\\"object\\\":\\\"text\\\",\\\"text\\\":\\\"check P4V URL here\\\",\\\"marks\\\":[{\\\"object\\\":\\\"mark\\\",\\\"type\\\":\\\"uui-richTextEditor-bold\\\",\\\"data\\\":{}}]}]},{\\\"object\\\":\\\"text\\\",\\\"text\\\":\\\"\\\",\\\"marks\\\":[{\\\"object\\\":\\\"mark\\\",\\\"type\\\":\\\"uui-richTextEditor-bold\\\",\\\"data\\\":{}}]}]}]},{\\\"object\\\":\\\"block\\\",\\\"type\\\":\\\"list-item\\\",\\\"data\\\":{},\\\"nodes\\\":[{\\\"object\\\":\\\"block\\\",\\\"type\\\":\\\"list-item-child\\\",\\\"data\\\":{},\\\"nodes\\\":[{\\\"object\\\":\\\"text\\\",\\\"text\\\":\\\"User: Use your LDAP login name\\\",\\\"marks\\\":[]}]}]},{\\\"object\\\":\\\"block\\\",\\\"type\\\":\\\"list-item\\\",\\\"data\\\":{},\\\"nodes\\\":[{\\\"object\\\":\\\"block\\\",\\\"type\\\":\\\"list-item-child\\\",\\\"data\\\":{},\\\"nodes\\\":[{\\\"object\\\":\\\"text\\\",\\\"text\\\":\\\"Workspace: Leave blank\\\",\\\"marks\\\":[]}]}]}]},{\\\"object\\\":\\\"block\\\",\\\"type\\\":\\\"paragraph\\\",\\\"data\\\":{},\\\"nodes\\\":[{\\\"object\\\":\\\"text\\\",\\\"text\\\":\\\"To create your workspace go to the Workspace tab on the main screen and choose 'New Workspace' option from the dropdown.\\\",\\\"marks\\\":[]}]},{\\\"object\\\":\\\"block\\\",\\\"type\\\":\\\"paragraph\\\",\\\"data\\\":{},\\\"nodes\\\":[{\\\"object\\\":\\\"text\\\",\\\"text\\\":\\\"Workspace name: Concatenate your LDAP login name and your machine’s name.\\\\nWorkspace root: Set the path where the source’ll be mapped. Note: Great idea to map the root on SSD if you have any. Important: Try to keep the path as short as possible! Long path’s names could cause trouble.\\\\nWorkspace mappings: Ask your team which branch is being used. They can help fine-tune your mappings as well.\\\",\\\"marks\\\":[]}]},{\\\"object\\\":\\\"block\\\",\\\"type\\\":\\\"paragraph\\\",\\\"data\\\":{},\\\"nodes\\\":[{\\\"object\\\":\\\"text\\\",\\\"text\\\":\\\"\\\",\\\"marks\\\":[]}]},{\\\"object\\\":\\\"block\\\",\\\"type\\\":\\\"separatorBLock\\\",\\\"data\\\":{},\\\"nodes\\\":[{\\\"object\\\":\\\"text\\\",\\\"text\\\":\\\"\\\",\\\"marks\\\":[{\\\"object\\\":\\\"mark\\\",\\\"type\\\":\\\"uui-richTextEditor-span-mark\\\",\\\"data\\\":{\\\"style\\\":{\\\"color\\\":\\\"rgb(70, 69, 71)\\\"}}}]}]},{\\\"object\\\":\\\"block\\\",\\\"type\\\":\\\"uui-richTextEditor-header-3\\\",\\\"data\\\":{},\\\"nodes\\\":[{\\\"object\\\":\\\"text\\\",\\\"text\\\":\\\"\\\",\\\"marks\\\":[{\\\"object\\\":\\\"mark\\\",\\\"type\\\":\\\"uui-richTextEditor-span-mark\\\",\\\"data\\\":{\\\"style\\\":{\\\"color\\\":\\\"rgb(70, 69, 71)\\\"}}}]}]},{\\\"object\\\":\\\"block\\\",\\\"type\\\":\\\"uui-richTextEditor-header-2\\\",\\\"data\\\":{},\\\"nodes\\\":[{\\\"object\\\":\\\"text\\\",\\\"text\\\":\\\"As a new recruit, use these steps to setup your computer (win 10)\\\",\\\"marks\\\":[{\\\"object\\\":\\\"mark\\\",\\\"type\\\":\\\"uui-richTextEditor-span-mark\\\",\\\"data\\\":{\\\"style\\\":{\\\"color\\\":\\\"#669900\\\"}}}]}]},{\\\"object\\\":\\\"block\\\",\\\"type\\\":\\\"paragraph\\\",\\\"data\\\":{},\\\"nodes\\\":[{\\\"object\\\":\\\"text\\\",\\\"text\\\":\\\"(You don't have to install each software, but we found them useful)\\\",\\\"marks\\\":[{\\\"object\\\":\\\"mark\\\",\\\"type\\\":\\\"uui-richTextEditor-span-mark\\\",\\\"data\\\":{\\\"style\\\":{\\\"color\\\":\\\"rgb(70, 69, 71)\\\"}}}]}]},{\\\"object\\\":\\\"block\\\",\\\"type\\\":\\\"paragraph\\\",\\\"data\\\":{},\\\"nodes\\\":[{\\\"object\\\":\\\"text\\\",\\\"text\\\":\\\" \\\",\\\"marks\\\":[{\\\"object\\\":\\\"mark\\\",\\\"type\\\":\\\"uui-richTextEditor-span-mark\\\",\\\"data\\\":{\\\"style\\\":{\\\"color\\\":\\\"rgb(70, 69, 71)\\\"}}}]}]},{\\\"object\\\":\\\"block\\\",\\\"type\\\":\\\"uui-richTextEditor-header-3\\\",\\\"data\\\":{},\\\"nodes\\\":[{\\\"object\\\":\\\"text\\\",\\\"text\\\":\\\"1. Install Visual Studios\\\",\\\"marks\\\":[]}]},{\\\"object\\\":\\\"block\\\",\\\"type\\\":\\\"paragraph\\\",\\\"data\\\":{},\\\"nodes\\\":[{\\\"object\\\":\\\"text\\\",\\\"text\\\":\\\"\\\\\\\\\\\\\\\\epam\\\\\\\\sam\\\\\\\\SoftArchive\\\\\\\\Dot_Net Developer\\\\\\\\\\\\na, Install VS 2012\\\\ni. Download and Install VS 2012 update 5\\\\nb, Install VS 2013\\\\ni. Download and Install VS 2013 update 5\\\\nc, Install VS 2015\\\",\\\"marks\\\":[]}]},{\\\"object\\\":\\\"block\\\",\\\"type\\\":\\\"paragraph\\\",\\\"data\\\":{},\\\"nodes\\\":[{\\\"object\\\":\\\"text\\\",\\\"text\\\":\\\" \\\",\\\"marks\\\":[{\\\"object\\\":\\\"mark\\\",\\\"type\\\":\\\"uui-richTextEditor-span-mark\\\",\\\"data\\\":{\\\"style\\\":{\\\"color\\\":\\\"rgb(70, 69, 71)\\\"}}}]}]},{\\\"object\\\":\\\"block\\\",\\\"type\\\":\\\"uui-richTextEditor-header-3\\\",\\\"data\\\":{},\\\"nodes\\\":[{\\\"object\\\":\\\"text\\\",\\\"text\\\":\\\"2. Download Pulse Secure\\\",\\\"marks\\\":[]}]},{\\\"object\\\":\\\"block\\\",\\\"type\\\":\\\"paragraph\\\",\\\"data\\\":{},\\\"nodes\\\":[{\\\"object\\\":\\\"text\\\",\\\"text\\\":\\\" \\\",\\\"marks\\\":[{\\\"object\\\":\\\"mark\\\",\\\"type\\\":\\\"uui-richTextEditor-span-mark\\\",\\\"data\\\":{\\\"style\\\":{\\\"color\\\":\\\"rgb(70, 69, 71)\\\"}}}]},{\\\"object\\\":\\\"inline\\\",\\\"type\\\":\\\"link\\\",\\\"data\\\":{\\\"url\\\":\\\"https://teamspace-sec.slb.com/sites/perimetersecurity/securegateway/LocalDocuments/Forms/AllItems.aspx\\\"},\\\"nodes\\\":[{\\\"object\\\":\\\"text\\\",\\\"text\\\":\\\"https://teamspace-sec.slb.com/sites/perimetersecurity/securegateway/LocalDocuments/Forms/AllItems.aspx\\\",\\\"marks\\\":[]}]},{\\\"object\\\":\\\"text\\\",\\\"text\\\":\\\"\\\\nUse Pulse Secure for XCAP users - How to install\\\",\\\"marks\\\":[]}]},{\\\"object\\\":\\\"block\\\",\\\"type\\\":\\\"paragraph\\\",\\\"data\\\":{},\\\"nodes\\\":[{\\\"object\\\":\\\"text\\\",\\\"text\\\":\\\"\\\",\\\"marks\\\":[{\\\"object\\\":\\\"mark\\\",\\\"type\\\":\\\"uui-richTextEditor-span-mark\\\",\\\"data\\\":{\\\"style\\\":{\\\"color\\\":\\\"rgb(70, 69, 71)\\\"}}}]}]},{\\\"object\\\":\\\"block\\\",\\\"type\\\":\\\"uui-richTextEditor-header-3\\\",\\\"data\\\":{},\\\"nodes\\\":[{\\\"object\\\":\\\"text\\\",\\\"text\\\":\\\"3. Get Entrust IdentityGuard\\\",\\\"marks\\\":[]}]},{\\\"object\\\":\\\"block\\\",\\\"type\\\":\\\"paragraph\\\",\\\"data\\\":{},\\\"nodes\\\":[{\\\"object\\\":\\\"text\\\",\\\"text\\\":\\\"First get untainted\\\\nGuide:\\\",\\\"marks\\\":[]},{\\\"object\\\":\\\"text\\\",\\\"text\\\":\\\" \\\",\\\"marks\\\":[{\\\"object\\\":\\\"mark\\\",\\\"type\\\":\\\"uui-richTextEditor-span-mark\\\",\\\"data\\\":{\\\"style\\\":{}}}]},{\\\"object\\\":\\\"inline\\\",\\\"type\\\":\\\"link\\\",\\\"data\\\":{\\\"url\\\":\\\"https://gateway.slb.com/Docs/tt/nws/mnsa/secureGateway/,DanaInfo=www.hub.slb.com,SSO=U+EntrustIDG-UserGuide-v3.pdf\\\"},\\\"nodes\\\":[{\\\"object\\\":\\\"text\\\",\\\"text\\\":\\\"https://gateway.slb.com/Docs/tt/nws/mnsa/secureGateway/,DanaInfo=www.hub.slb.com,SSO=U+EntrustIDG-UserGuide-v3.pdf\\\",\\\"marks\\\":[]}]},{\\\"object\\\":\\\"text\\\",\\\"text\\\":\\\"\\\\n\\\",\\\"marks\\\":[]},{\\\"object\\\":\\\"inline\\\",\\\"type\\\":\\\"link\\\",\\\"data\\\":{\\\"url\\\":\\\"https://gateway.slb.com/mytoken\\\"},\\\"nodes\\\":[{\\\"object\\\":\\\"text\\\",\\\"text\\\":\\\"https://gateway.slb.com/mytoken\\\",\\\"marks\\\":[]}]},{\\\"object\\\":\\\"text\\\",\\\"text\\\":\\\" \\\",\\\"marks\\\":[{\\\"object\\\":\\\"mark\\\",\\\"type\\\":\\\"uui-richTextEditor-span-mark\\\",\\\"data\\\":{\\\"style\\\":{}}}]},{\\\"object\\\":\\\"text\\\",\\\"text\\\":\\\"register for Entrust SoftToken\\\",\\\"marks\\\":[]}]},{\\\"object\\\":\\\"block\\\",\\\"type\\\":\\\"paragraph\\\",\\\"data\\\":{},\\\"nodes\\\":[{\\\"object\\\":\\\"text\\\",\\\"text\\\":\\\" \\\",\\\"marks\\\":[{\\\"object\\\":\\\"mark\\\",\\\"type\\\":\\\"uui-richTextEditor-span-mark\\\",\\\"data\\\":{\\\"style\\\":{\\\"color\\\":\\\"rgb(70, 69, 71)\\\"}}}]}]},{\\\"object\\\":\\\"block\\\",\\\"type\\\":\\\"uui-richTextEditor-header-3\\\",\\\"data\\\":{},\\\"nodes\\\":[{\\\"object\\\":\\\"text\\\",\\\"text\\\":\\\"4. Get perforce (P4) client\\\",\\\"marks\\\":[]}]},{\\\"object\\\":\\\"block\\\",\\\"type\\\":\\\"paragraph\\\",\\\"data\\\":{},\\\"nodes\\\":[{\\\"object\\\":\\\"text\\\",\\\"text\\\":\\\"\\\",\\\"marks\\\":[]},{\\\"object\\\":\\\"inline\\\",\\\"type\\\":\\\"link\\\",\\\"data\\\":{\\\"url\\\":\\\"https://www.perforce.com/downloads/helix#product-9\\\"},\\\"nodes\\\":[{\\\"object\\\":\\\"text\\\",\\\"text\\\":\\\"https://www.perforce.com/downloads/helix#product-9\\\",\\\"marks\\\":[]}]},{\\\"object\\\":\\\"text\\\",\\\"text\\\":\\\"\\\\nHelix p4v: visual client\\\\nconnect:\\\",\\\"marks\\\":[]},{\\\"object\\\":\\\"text\\\",\\\"text\\\":\\\" \\\",\\\"marks\\\":[{\\\"object\\\":\\\"mark\\\",\\\"type\\\":\\\"uui-richTextEditor-span-mark\\\",\\\"data\\\":{\\\"style\\\":{}}}]},{\\\"object\\\":\\\"inline\\\",\\\"type\\\":\\\"link\\\",\\\"data\\\":{\\\"url\\\":\\\"http://srvoslperf.dir.slb.com/\\\"},\\\"nodes\\\":[{\\\"object\\\":\\\"text\\\",\\\"text\\\":\\\"srvoslperf.dir.slb.com\\\",\\\"marks\\\":[]}]},{\\\"object\\\":\\\"text\\\",\\\"text\\\":\\\":1666, username, UserName (note cases)\\\\n\\\\n\\\",\\\"marks\\\":[]}]},{\\\"object\\\":\\\"block\\\",\\\"type\\\":\\\"uui-richTextEditor-header-3\\\",\\\"data\\\":{},\\\"nodes\\\":[{\\\"object\\\":\\\"text\\\",\\\"text\\\":\\\"5. Setup Outlook\\\",\\\"marks\\\":[]}]},{\\\"object\\\":\\\"block\\\",\\\"type\\\":\\\"paragraph\\\",\\\"data\\\":{},\\\"nodes\\\":[{\\\"object\\\":\\\"text\\\",\\\"text\\\":\\\"disconnect pulse secure\\\\nuse slb account\\\\n\\\",\\\"marks\\\":[]}]},{\\\"object\\\":\\\"block\\\",\\\"type\\\":\\\"uui-richTextEditor-header-3\\\",\\\"data\\\":{},\\\"nodes\\\":[{\\\"object\\\":\\\"text\\\",\\\"text\\\":\\\"6. Apply for resharper license\\\",\\\"marks\\\":[]}]},{\\\"object\\\":\\\"block\\\",\\\"type\\\":\\\"paragraph\\\",\\\"data\\\":{},\\\"nodes\\\":[{\\\"object\\\":\\\"text\\\",\\\"text\\\":\\\"Install resharper c# and\\\\nTeamcity addin\\\",\\\"marks\\\":[]}]},{\\\"object\\\":\\\"block\\\",\\\"type\\\":\\\"uui-richTextEditor-header-3\\\",\\\"data\\\":{},\\\"nodes\\\":[{\\\"object\\\":\\\"text\\\",\\\"text\\\":\\\"\\\\n\\\\n7. Install 7zip\\\",\\\"marks\\\":[]}]},{\\\"object\\\":\\\"block\\\",\\\"type\\\":\\\"uui-richTextEditor-header-3\\\",\\\"data\\\":{},\\\"nodes\\\":[{\\\"object\\\":\\\"text\\\",\\\"text\\\":\\\" \\\",\\\"marks\\\":[{\\\"object\\\":\\\"mark\\\",\\\"type\\\":\\\"uui-richTextEditor-span-mark\\\",\\\"data\\\":{\\\"style\\\":{\\\"color\\\":\\\"rgb(70, 69, 71)\\\"}}}]}]},{\\\"object\\\":\\\"block\\\",\\\"type\\\":\\\"uui-richTextEditor-header-3\\\",\\\"data\\\":{},\\\"nodes\\\":[{\\\"object\\\":\\\"text\\\",\\\"text\\\":\\\"8. Install skype\\\",\\\"marks\\\":[]}]},{\\\"object\\\":\\\"block\\\",\\\"type\\\":\\\"uui-richTextEditor-header-3\\\",\\\"data\\\":{},\\\"nodes\\\":[{\\\"object\\\":\\\"text\\\",\\\"text\\\":\\\" \\\",\\\"marks\\\":[{\\\"object\\\":\\\"mark\\\",\\\"type\\\":\\\"uui-richTextEditor-span-mark\\\",\\\"data\\\":{\\\"style\\\":{\\\"color\\\":\\\"rgb(70, 69, 71)\\\"}}}]}]},{\\\"object\\\":\\\"block\\\",\\\"type\\\":\\\"uui-richTextEditor-header-3\\\",\\\"data\\\":{},\\\"nodes\\\":[{\\\"object\\\":\\\"text\\\",\\\"text\\\":\\\"9. Install Lync\\\",\\\"marks\\\":[]}]},{\\\"object\\\":\\\"block\\\",\\\"type\\\":\\\"uui-richTextEditor-header-3\\\",\\\"data\\\":{},\\\"nodes\\\":[{\\\"object\\\":\\\"text\\\",\\\"text\\\":\\\" \\\",\\\"marks\\\":[{\\\"object\\\":\\\"mark\\\",\\\"type\\\":\\\"uui-richTextEditor-span-mark\\\",\\\"data\\\":{\\\"style\\\":{\\\"color\\\":\\\"rgb(70, 69, 71)\\\"}}}]}]},{\\\"object\\\":\\\"block\\\",\\\"type\\\":\\\"uui-richTextEditor-header-3\\\",\\\"data\\\":{},\\\"nodes\\\":[{\\\"object\\\":\\\"text\\\",\\\"text\\\":\\\"10. Install Printer (xyz17)\\\",\\\"marks\\\":[]}]},{\\\"object\\\":\\\"block\\\",\\\"type\\\":\\\"uui-richTextEditor-header-3\\\",\\\"data\\\":{},\\\"nodes\\\":[{\\\"object\\\":\\\"text\\\",\\\"text\\\":\\\" \\\",\\\"marks\\\":[{\\\"object\\\":\\\"mark\\\",\\\"type\\\":\\\"uui-richTextEditor-span-mark\\\",\\\"data\\\":{\\\"style\\\":{\\\"color\\\":\\\"rgb(70, 69, 71)\\\"}}}]}]},{\\\"object\\\":\\\"block\\\",\\\"type\\\":\\\"uui-richTextEditor-header-3\\\",\\\"data\\\":{},\\\"nodes\\\":[{\\\"object\\\":\\\"text\\\",\\\"text\\\":\\\"11. Instal total commander\\\",\\\"marks\\\":[]}]},{\\\"object\\\":\\\"block\\\",\\\"type\\\":\\\"paragraph\\\",\\\"data\\\":{},\\\"nodes\\\":[{\\\"object\\\":\\\"text\\\",\\\"text\\\":\\\" \\\",\\\"marks\\\":[{\\\"object\\\":\\\"mark\\\",\\\"type\\\":\\\"uui-richTextEditor-span-mark\\\",\\\"data\\\":{\\\"style\\\":{\\\"color\\\":\\\"rgb(70, 69, 71)\\\"}}}]}]},{\\\"object\\\":\\\"block\\\",\\\"type\\\":\\\"uui-richTextEditor-header-3\\\",\\\"data\\\":{},\\\"nodes\\\":[{\\\"object\\\":\\\"text\\\",\\\"text\\\":\\\"12. Instal virtual box\\\",\\\"marks\\\":[]}]},{\\\"object\\\":\\\"block\\\",\\\"type\\\":\\\"paragraph\\\",\\\"data\\\":{},\\\"nodes\\\":[{\\\"object\\\":\\\"text\\\",\\\"text\\\":\\\"\\\\n\\\\\\\\\\\\\\\\\\\",\\\"marks\\\":[]},{\\\"object\\\":\\\"inline\\\",\\\"type\\\":\\\"link\\\",\\\"data\\\":{\\\"url\\\":\\\"http://epam.com/\\\"},\\\"nodes\\\":[{\\\"object\\\":\\\"text\\\",\\\"text\\\":\\\"epam.com\\\",\\\"marks\\\":[]}]},{\\\"object\\\":\\\"text\\\",\\\"text\\\":\\\"\\\\\\\\sam\\\\\\\\SoftArchive\\\\\\\\EPAM_Images\\\\\\\\\\\\n\\\\\\\\\\\\\\\\\\\",\\\"marks\\\":[]},{\\\"object\\\":\\\"inline\\\",\\\"type\\\":\\\"link\\\",\\\"data\\\":{\\\"url\\\":\\\"http://epam.com/\\\"},\\\"nodes\\\":[{\\\"object\\\":\\\"text\\\",\\\"text\\\":\\\"epam.com\\\",\\\"marks\\\":[]}]},{\\\"object\\\":\\\"text\\\",\\\"text\\\":\\\"\\\\\\\\sam\\\\\\\\SoftArchive\\\\\\\\Base\\\\\\\\Oracle\\\\\\\\Virtual_BOX\\\\\\\\\\\\nTURN Hyper-V off (turn of windows features)\\\\n\\\",\\\"marks\\\":[]}]},{\\\"object\\\":\\\"block\\\",\\\"type\\\":\\\"uui-richTextEditor-header-3\\\",\\\"data\\\":{},\\\"nodes\\\":[{\\\"object\\\":\\\"text\\\",\\\"text\\\":\\\"13. Install notepad ++\\\",\\\"marks\\\":[]}]},{\\\"object\\\":\\\"block\\\",\\\"type\\\":\\\"paragraph\\\",\\\"data\\\":{},\\\"nodes\\\":[{\\\"object\\\":\\\"text\\\",\\\"text\\\":\\\" \\\",\\\"marks\\\":[{\\\"object\\\":\\\"mark\\\",\\\"type\\\":\\\"uui-richTextEditor-span-mark\\\",\\\"data\\\":{\\\"style\\\":{\\\"color\\\":\\\"rgb(70, 69, 71)\\\"}}}]}]},{\\\"object\\\":\\\"block\\\",\\\"type\\\":\\\"uui-richTextEditor-header-3\\\",\\\"data\\\":{},\\\"nodes\\\":[{\\\"object\\\":\\\"text\\\",\\\"text\\\":\\\"14. Setup Teamcity\\\",\\\"marks\\\":[]}]},{\\\"object\\\":\\\"block\\\",\\\"type\\\":\\\"paragraph\\\",\\\"data\\\":{},\\\"nodes\\\":[{\\\"object\\\":\\\"text\\\",\\\"text\\\":\\\" \\\",\\\"marks\\\":[{\\\"object\\\":\\\"mark\\\",\\\"type\\\":\\\"uui-richTextEditor-span-mark\\\",\\\"data\\\":{\\\"style\\\":{\\\"color\\\":\\\"rgb(70, 69, 71)\\\"}}}]},{\\\"object\\\":\\\"inline\\\",\\\"type\\\":\\\"link\\\",\\\"data\\\":{\\\"url\\\":\\\"http://teamcityosl.dir.slb.com/\\\"},\\\"nodes\\\":[{\\\"object\\\":\\\"text\\\",\\\"text\\\":\\\"http://teamcityosl.dir.slb.com/\\\",\\\"marks\\\":[]}]},{\\\"object\\\":\\\"text\\\",\\\"text\\\":\\\"\\\\n\\\",\\\"marks\\\":[]},{\\\"object\\\":\\\"inline\\\",\\\"type\\\":\\\"link\\\",\\\"data\\\":{\\\"url\\\":\\\"http://teamcityosl.dir.slb.com/\\\"},\\\"nodes\\\":[{\\\"object\\\":\\\"text\\\",\\\"text\\\":\\\"dir\\\\\\\\username\\\\nldap pass\\\\npulse mu\\\",\\\"marks\\\":[]}]},{\\\"object\\\":\\\"text\\\",\\\"text\\\":\\\"st be connected\\\",\\\"marks\\\":[]}]},{\\\"object\\\":\\\"block\\\",\\\"type\\\":\\\"paragraph\\\",\\\"data\\\":{},\\\"nodes\\\":[{\\\"object\\\":\\\"text\\\",\\\"text\\\":\\\"\\\",\\\"marks\\\":[]}]},{\\\"object\\\":\\\"block\\\",\\\"type\\\":\\\"uui-richTextEditor-header-3\\\",\\\"data\\\":{},\\\"nodes\\\":[{\\\"object\\\":\\\"text\\\",\\\"text\\\":\\\"15. Set registry\\\",\\\"marks\\\":[]}]},{\\\"object\\\":\\\"block\\\",\\\"type\\\":\\\"paragraph\\\",\\\"data\\\":{},\\\"nodes\\\":[{\\\"object\\\":\\\"text\\\",\\\"text\\\":\\\"HKEY_CURRENT_USER\\\\\\\\\\\",\\\"marks\\\":[]},{\\\"object\\\":\\\"inline\\\",\\\"type\\\":\\\"link\\\",\\\"data\\\":{\\\"url\\\":\\\"http://www.perforce.com/downloads/helix#product-9Configuring\\\"},\\\"nodes\\\":[{\\\"object\\\":\\\"text\\\",\\\"text\\\":\\\"Control Panel\\\\\\\\Desktop\\\\\\\\ScreenSaveTimeOut = 600\\\",\\\"marks\\\":[]}]},{\\\"object\\\":\\\"text\\\",\\\"text\\\":\\\"\\\",\\\"marks\\\":[]}]},{\\\"object\\\":\\\"block\\\",\\\"type\\\":\\\"uui-richTextEditor-header-3\\\",\\\"data\\\":{},\\\"nodes\\\":[{\\\"object\\\":\\\"text\\\",\\\"text\\\":\\\"\\\",\\\"marks\\\":[]}]}]}}\""}