{"content":"\"{\\\"object\\\":\\\"value\\\",\\\"document\\\":{\\\"object\\\":\\\"document\\\",\\\"data\\\":{},\\\"nodes\\\":[{\\\"object\\\":\\\"block\\\",\\\"type\\\":\\\"uui-richTextEditor-header-2\\\",\\\"data\\\":{},\\\"nodes\\\":[{\\\"object\\\":\\\"text\\\",\\\"text\\\":\\\"Информационный ресурс PAL\\\",\\\"marks\\\":[{\\\"object\\\":\\\"mark\\\",\\\"type\\\":\\\"uui-richTextEditor-bold\\\",\\\"data\\\":{}}]}]},{\\\"object\\\":\\\"block\\\",\\\"type\\\":\\\"paragraph\\\",\\\"data\\\":{},\\\"nodes\\\":[{\\\"object\\\":\\\"text\\\",\\\"text\\\":\\\"\\\",\\\"marks\\\":[]},{\\\"object\\\":\\\"inline\\\",\\\"type\\\":\\\"link\\\",\\\"data\\\":{\\\"url\\\":\\\"https://pal.epam.com/\\\"},\\\"nodes\\\":[{\\\"object\\\":\\\"text\\\",\\\"text\\\":\\\"EPAM Process Asset Library (PAL)\\\",\\\"marks\\\":[{\\\"object\\\":\\\"mark\\\",\\\"type\\\":\\\"uui-richTextEditor-bold\\\",\\\"data\\\":{}}]}]},{\\\"object\\\":\\\"text\\\",\\\"text\\\":\\\" — внутренний информационный ресурс, который обеспечивает доступ к EPAM QMS\\\",\\\"marks\\\":[]},{\\\"object\\\":\\\"text\\\",\\\"text\\\":\\\" \\\",\\\"marks\\\":[{\\\"object\\\":\\\"mark\\\",\\\"type\\\":\\\"uui-richTextEditor-span-mark\\\",\\\"data\\\":{\\\"style\\\":{}}}]},{\\\"object\\\":\\\"text\\\",\\\"text\\\":\\\"и\\\",\\\"marks\\\":[{\\\"object\\\":\\\"mark\\\",\\\"type\\\":\\\"uui-richTextEditor-span-mark\\\",\\\"data\\\":{\\\"style\\\":{}}}]},{\\\"object\\\":\\\"text\\\",\\\"text\\\":\\\" \\\",\\\"marks\\\":[{\\\"object\\\":\\\"mark\\\",\\\"type\\\":\\\"uui-richTextEditor-span-mark\\\",\\\"data\\\":{\\\"style\\\":{}}},{\\\"object\\\":\\\"mark\\\",\\\"type\\\":\\\"uui-richTextEditor-span-mark\\\",\\\"data\\\":{\\\"style\\\":{}}}]},{\\\"object\\\":\\\"text\\\",\\\"text\\\":\\\"ISMS\\\",\\\"marks\\\":[]},{\\\"object\\\":\\\"text\\\",\\\"text\\\":\\\" \\\",\\\"marks\\\":[{\\\"object\\\":\\\"mark\\\",\\\"type\\\":\\\"uui-richTextEditor-span-mark\\\",\\\"data\\\":{\\\"style\\\":{}}}]},{\\\"object\\\":\\\"text\\\",\\\"text\\\":\\\"документации.\\\",\\\"marks\\\":[{\\\"object\\\":\\\"mark\\\",\\\"type\\\":\\\"uui-richTextEditor-span-mark\\\",\\\"data\\\":{\\\"style\\\":{}}}]}]},{\\\"object\\\":\\\"block\\\",\\\"type\\\":\\\"paragraph\\\",\\\"data\\\":{},\\\"nodes\\\":[{\\\"object\\\":\\\"text\\\",\\\"text\\\":\\\" На главной странице PAL\\\",\\\"marks\\\":[]},{\\\"object\\\":\\\"text\\\",\\\"text\\\":\\\" \\\",\\\"marks\\\":[{\\\"object\\\":\\\"mark\\\",\\\"type\\\":\\\"uui-richTextEditor-span-mark\\\",\\\"data\\\":{\\\"style\\\":{}}}]},{\\\"object\\\":\\\"text\\\",\\\"text\\\":\\\"имеются три вкладки:\\\",\\\"marks\\\":[{\\\"object\\\":\\\"mark\\\",\\\"type\\\":\\\"uui-richTextEditor-span-mark\\\",\\\"data\\\":{\\\"style\\\":{}}}]}]},{\\\"object\\\":\\\"block\\\",\\\"type\\\":\\\"ordered-list\\\",\\\"data\\\":{},\\\"nodes\\\":[{\\\"object\\\":\\\"block\\\",\\\"type\\\":\\\"list-item\\\",\\\"data\\\":{},\\\"nodes\\\":[{\\\"object\\\":\\\"block\\\",\\\"type\\\":\\\"list-item-child\\\",\\\"data\\\":{},\\\"nodes\\\":[{\\\"object\\\":\\\"text\\\",\\\"text\\\":\\\"PAL\\\",\\\"marks\\\":[]},{\\\"object\\\":\\\"text\\\",\\\"text\\\":\\\" \\\",\\\"marks\\\":[{\\\"object\\\":\\\"mark\\\",\\\"type\\\":\\\"uui-richTextEditor-span-mark\\\",\\\"data\\\":{\\\"style\\\":{}}}]},{\\\"object\\\":\\\"text\\\",\\\"text\\\":\\\"– содержит информацию о\\\",\\\"marks\\\":[{\\\"object\\\":\\\"mark\\\",\\\"type\\\":\\\"uui-richTextEditor-span-mark\\\",\\\"data\\\":{\\\"style\\\":{}}}]},{\\\"object\\\":\\\"text\\\",\\\"text\\\":\\\" \\\",\\\"marks\\\":[{\\\"object\\\":\\\"mark\\\",\\\"type\\\":\\\"uui-richTextEditor-span-mark\\\",\\\"data\\\":{\\\"style\\\":{}}},{\\\"object\\\":\\\"mark\\\",\\\"type\\\":\\\"uui-richTextEditor-span-mark\\\",\\\"data\\\":{\\\"style\\\":{}}}]},{\\\"object\\\":\\\"text\\\",\\\"text\\\":\\\"EPAM QMS\\\",\\\"marks\\\":[]},{\\\"object\\\":\\\"text\\\",\\\"text\\\":\\\" \\\",\\\"marks\\\":[{\\\"object\\\":\\\"mark\\\",\\\"type\\\":\\\"uui-richTextEditor-span-mark\\\",\\\"data\\\":{\\\"style\\\":{}}}]},{\\\"object\\\":\\\"text\\\",\\\"text\\\":\\\"и\\\",\\\"marks\\\":[{\\\"object\\\":\\\"mark\\\",\\\"type\\\":\\\"uui-richTextEditor-span-mark\\\",\\\"data\\\":{\\\"style\\\":{}}}]},{\\\"object\\\":\\\"text\\\",\\\"text\\\":\\\" \\\",\\\"marks\\\":[{\\\"object\\\":\\\"mark\\\",\\\"type\\\":\\\"uui-richTextEditor-span-mark\\\",\\\"data\\\":{\\\"style\\\":{}}},{\\\"object\\\":\\\"mark\\\",\\\"type\\\":\\\"uui-richTextEditor-span-mark\\\",\\\"data\\\":{\\\"style\\\":{}}}]},{\\\"object\\\":\\\"text\\\",\\\"text\\\":\\\"ISMS\\\",\\\"marks\\\":[]},{\\\"object\\\":\\\"text\\\",\\\"text\\\":\\\" \\\",\\\"marks\\\":[{\\\"object\\\":\\\"mark\\\",\\\"type\\\":\\\"uui-richTextEditor-span-mark\\\",\\\"data\\\":{\\\"style\\\":{}}}]},{\\\"object\\\":\\\"text\\\",\\\"text\\\":\\\"документации, сгруппированную по главным\\\",\\\"marks\\\":[{\\\"object\\\":\\\"mark\\\",\\\"type\\\":\\\"uui-richTextEditor-span-mark\\\",\\\"data\\\":{\\\"style\\\":{}}}]},{\\\"object\\\":\\\"text\\\",\\\"text\\\":\\\" \\\",\\\"marks\\\":[{\\\"object\\\":\\\"mark\\\",\\\"type\\\":\\\"uui-richTextEditor-span-mark\\\",\\\"data\\\":{\\\"style\\\":{}}},{\\\"object\\\":\\\"mark\\\",\\\"type\\\":\\\"uui-richTextEditor-span-mark\\\",\\\"data\\\":{\\\"style\\\":{}}}]},{\\\"object\\\":\\\"text\\\",\\\"text\\\":\\\"QMS\\\",\\\"marks\\\":[]},{\\\"object\\\":\\\"text\\\",\\\"text\\\":\\\" \\\",\\\"marks\\\":[{\\\"object\\\":\\\"mark\\\",\\\"type\\\":\\\"uui-richTextEditor-span-mark\\\",\\\"data\\\":{\\\"style\\\":{}}}]},{\\\"object\\\":\\\"text\\\",\\\"text\\\":\\\"темам;\\\",\\\"marks\\\":[{\\\"object\\\":\\\"mark\\\",\\\"type\\\":\\\"uui-richTextEditor-span-mark\\\",\\\"data\\\":{\\\"style\\\":{}}}]}]}]},{\\\"object\\\":\\\"block\\\",\\\"type\\\":\\\"list-item\\\",\\\"data\\\":{},\\\"nodes\\\":[{\\\"object\\\":\\\"block\\\",\\\"type\\\":\\\"list-item-child\\\",\\\"data\\\":{},\\\"nodes\\\":[{\\\"object\\\":\\\"text\\\",\\\"text\\\":\\\"Roles – содержит описание существующих в EPAM\\\",\\\"marks\\\":[]},{\\\"object\\\":\\\"text\\\",\\\"text\\\":\\\" \\\",\\\"marks\\\":[{\\\"object\\\":\\\"mark\\\",\\\"type\\\":\\\"uui-richTextEditor-span-mark\\\",\\\"data\\\":{\\\"style\\\":{}}}]},{\\\"object\\\":\\\"text\\\",\\\"text\\\":\\\"проектных и процессных ролей;\\\",\\\"marks\\\":[{\\\"object\\\":\\\"mark\\\",\\\"type\\\":\\\"uui-richTextEditor-span-mark\\\",\\\"data\\\":{\\\"style\\\":{}}}]}]}]},{\\\"object\\\":\\\"block\\\",\\\"type\\\":\\\"list-item\\\",\\\"data\\\":{},\\\"nodes\\\":[{\\\"object\\\":\\\"block\\\",\\\"type\\\":\\\"list-item-child\\\",\\\"data\\\":{},\\\"nodes\\\":[{\\\"object\\\":\\\"text\\\",\\\"text\\\":\\\"EPAM Regulations\\\",\\\"marks\\\":[]},{\\\"object\\\":\\\"text\\\",\\\"text\\\":\\\" \\\",\\\"marks\\\":[{\\\"object\\\":\\\"mark\\\",\\\"type\\\":\\\"uui-richTextEditor-span-mark\\\",\\\"data\\\":{\\\"style\\\":{}}}]},{\\\"object\\\":\\\"text\\\",\\\"text\\\":\\\"–\\\",\\\"marks\\\":[{\\\"object\\\":\\\"mark\\\",\\\"type\\\":\\\"uui-richTextEditor-span-mark\\\",\\\"data\\\":{\\\"style\\\":{}}}]},{\\\"object\\\":\\\"text\\\",\\\"text\\\":\\\" \\\",\\\"marks\\\":[{\\\"object\\\":\\\"mark\\\",\\\"type\\\":\\\"uui-richTextEditor-span-mark\\\",\\\"data\\\":{\\\"style\\\":{}}}]},{\\\"object\\\":\\\"text\\\",\\\"text\\\":\\\"содержит нормативные акты EPAM, сгруппированные по типам существующих артефактов.\\\",\\\"marks\\\":[]}]}]}]},{\\\"object\\\":\\\"block\\\",\\\"type\\\":\\\"image\\\",\\\"data\\\":{\\\"src\\\":\\\"https://onboarding.epam.com/app/cdn/6d089717-b149-46c5-8172-1f50c8118997/Capture.PNG\\\",\\\"imageSize\\\":{\\\"width\\\":1366,\\\"height\\\":629}},\\\"nodes\\\":[{\\\"object\\\":\\\"text\\\",\\\"text\\\":\\\"\\\",\\\"marks\\\":[]}]},{\\\"object\\\":\\\"block\\\",\\\"type\\\":\\\"paragraph\\\",\\\"data\\\":{},\\\"nodes\\\":[{\\\"object\\\":\\\"text\\\",\\\"text\\\":\\\"\\\\n\\\",\\\"marks\\\":[{\\\"object\\\":\\\"mark\\\",\\\"type\\\":\\\"uui-richTextEditor-bold\\\",\\\"data\\\":{}}]}]},{\\\"object\\\":\\\"block\\\",\\\"type\\\":\\\"paragraph\\\",\\\"data\\\":{},\\\"nodes\\\":[{\\\"object\\\":\\\"text\\\",\\\"text\\\":\\\"EPAM QMS\\\",\\\"marks\\\":[]},{\\\"object\\\":\\\"text\\\",\\\"text\\\":\\\" \\\",\\\"marks\\\":[{\\\"object\\\":\\\"mark\\\",\\\"type\\\":\\\"uui-richTextEditor-span-mark\\\",\\\"data\\\":{\\\"style\\\":{}}}]},{\\\"object\\\":\\\"text\\\",\\\"text\\\":\\\"и\\\",\\\"marks\\\":[{\\\"object\\\":\\\"mark\\\",\\\"type\\\":\\\"uui-richTextEditor-span-mark\\\",\\\"data\\\":{\\\"style\\\":{}}}]},{\\\"object\\\":\\\"text\\\",\\\"text\\\":\\\" \\\",\\\"marks\\\":[{\\\"object\\\":\\\"mark\\\",\\\"type\\\":\\\"uui-richTextEditor-span-mark\\\",\\\"data\\\":{\\\"style\\\":{}}},{\\\"object\\\":\\\"mark\\\",\\\"type\\\":\\\"uui-richTextEditor-span-mark\\\",\\\"data\\\":{\\\"style\\\":{}}}]},{\\\"object\\\":\\\"text\\\",\\\"text\\\":\\\"ISMS\\\",\\\"marks\\\":[]},{\\\"object\\\":\\\"text\\\",\\\"text\\\":\\\" \\\",\\\"marks\\\":[{\\\"object\\\":\\\"mark\\\",\\\"type\\\":\\\"uui-richTextEditor-span-mark\\\",\\\"data\\\":{\\\"style\\\":{}}}]},{\\\"object\\\":\\\"text\\\",\\\"text\\\":\\\"определяют любую документированную информацию как\\\",\\\"marks\\\":[{\\\"object\\\":\\\"mark\\\",\\\"type\\\":\\\"uui-richTextEditor-span-mark\\\",\\\"data\\\":{\\\"style\\\":{}}}]},{\\\"object\\\":\\\"text\\\",\\\"text\\\":\\\" \\\",\\\"marks\\\":[{\\\"object\\\":\\\"mark\\\",\\\"type\\\":\\\"uui-richTextEditor-span-mark\\\",\\\"data\\\":{\\\"style\\\":{}}},{\\\"object\\\":\\\"mark\\\",\\\"type\\\":\\\"uui-richTextEditor-span-mark\\\",\\\"data\\\":{\\\"style\\\":{}}}]},{\\\"object\\\":\\\"text\\\",\\\"text\\\":\\\"артифакт\\\",\\\"marks\\\":[{\\\"object\\\":\\\"mark\\\",\\\"type\\\":\\\"uui-richTextEditor-bold\\\",\\\"data\\\":{}},{\\\"object\\\":\\\"mark\\\",\\\"type\\\":\\\"uui-richTextEditor-span-mark\\\",\\\"data\\\":{\\\"style\\\":{}}}]},{\\\"object\\\":\\\"text\\\",\\\"text\\\":\\\".\\\",\\\"marks\\\":[{\\\"object\\\":\\\"mark\\\",\\\"type\\\":\\\"uui-richTextEditor-span-mark\\\",\\\"data\\\":{\\\"style\\\":{}}}]}]},{\\\"object\\\":\\\"block\\\",\\\"type\\\":\\\"paragraph\\\",\\\"data\\\":{},\\\"nodes\\\":[{\\\"object\\\":\\\"text\\\",\\\"text\\\":\\\"Выделяют следующие группы артифактов:\\\",\\\"marks\\\":[]}]},{\\\"object\\\":\\\"block\\\",\\\"type\\\":\\\"unordered-list\\\",\\\"data\\\":{},\\\"nodes\\\":[{\\\"object\\\":\\\"block\\\",\\\"type\\\":\\\"list-item\\\",\\\"data\\\":{},\\\"nodes\\\":[{\\\"object\\\":\\\"block\\\",\\\"type\\\":\\\"list-item-child\\\",\\\"data\\\":{},\\\"nodes\\\":[{\\\"object\\\":\\\"text\\\",\\\"text\\\":\\\"Артефакты внешнего происхождения\\\",\\\"marks\\\":[{\\\"object\\\":\\\"mark\\\",\\\"type\\\":\\\"uui-richTextEditor-bold\\\",\\\"data\\\":{}}]},{\\\"object\\\":\\\"text\\\",\\\"text\\\":\\\" \\\",\\\"marks\\\":[{\\\"object\\\":\\\"mark\\\",\\\"type\\\":\\\"uui-richTextEditor-span-mark\\\",\\\"data\\\":{\\\"style\\\":{}}},{\\\"object\\\":\\\"mark\\\",\\\"type\\\":\\\"uui-richTextEditor-bold\\\",\\\"data\\\":{}}]},{\\\"object\\\":\\\"text\\\",\\\"text\\\":\\\"(нормативные документы, руководства, требования заказчика, сертификаты) включают в себя артефакты, разработанные внешней стороной и определенные EPAM как необходимые для планирования и функционирования QMS и ISMS;\\\",\\\"marks\\\":[]}]}]},{\\\"object\\\":\\\"block\\\",\\\"type\\\":\\\"list-item\\\",\\\"data\\\":{},\\\"nodes\\\":[{\\\"object\\\":\\\"block\\\",\\\"type\\\":\\\"list-item-child\\\",\\\"data\\\":{},\\\"nodes\\\":[{\\\"object\\\":\\\"text\\\",\\\"text\\\":\\\"Нормативные документы EPAM\\\",\\\"marks\\\":[{\\\"object\\\":\\\"mark\\\",\\\"type\\\":\\\"uui-richTextEditor-bold\\\",\\\"data\\\":{}}]},{\\\"object\\\":\\\"text\\\",\\\"text\\\":\\\" \\\",\\\"marks\\\":[{\\\"object\\\":\\\"mark\\\",\\\"type\\\":\\\"uui-richTextEditor-span-mark\\\",\\\"data\\\":{\\\"style\\\":{}}}]},{\\\"object\\\":\\\"text\\\",\\\"text\\\":\\\"- это набор документов, в которых описываются основные принципы работы в EPAM и которые включают в себя, но не ограничиваются ими:\\\",\\\"marks\\\":[]}]},{\\\"object\\\":\\\"block\\\",\\\"type\\\":\\\"unordered-list\\\",\\\"data\\\":{},\\\"nodes\\\":[{\\\"object\\\":\\\"block\\\",\\\"type\\\":\\\"list-item\\\",\\\"data\\\":{},\\\"nodes\\\":[{\\\"object\\\":\\\"block\\\",\\\"type\\\":\\\"list-item-child\\\",\\\"data\\\":{},\\\"nodes\\\":[{\\\"object\\\":\\\"text\\\",\\\"text\\\":\\\"Code of Ethical Conduct/ Кодекс этического поведения- документ, описывающий совокупность принципов поведения в соответствии с основными ценностями EPAM и этическими стандартами;\\\",\\\"marks\\\":[]}]}]},{\\\"object\\\":\\\"block\\\",\\\"type\\\":\\\"list-item\\\",\\\"data\\\":{},\\\"nodes\\\":[{\\\"object\\\":\\\"block\\\",\\\"type\\\":\\\"list-item-child\\\",\\\"data\\\":{},\\\"nodes\\\":[{\\\"object\\\":\\\"text\\\",\\\"text\\\":\\\"Corporate Governance Policy\\\",\\\"marks\\\":[]},{\\\"object\\\":\\\"text\\\",\\\"text\\\":\\\" \\\",\\\"marks\\\":[{\\\"object\\\":\\\"mark\\\",\\\"type\\\":\\\"uui-richTextEditor-span-mark\\\",\\\"data\\\":{\\\"style\\\":{}}}]},{\\\"object\\\":\\\"text\\\",\\\"text\\\":\\\"/ Политика корпоративного управления – документ, который описывает намерения и направление деятельности EPAM в конкретной области, формально выраженные ее высшим руководством;\\\",\\\"marks\\\":[{\\\"object\\\":\\\"mark\\\",\\\"type\\\":\\\"uui-richTextEditor-span-mark\\\",\\\"data\\\":{\\\"style\\\":{}}}]}]}]},{\\\"object\\\":\\\"block\\\",\\\"type\\\":\\\"list-item\\\",\\\"data\\\":{},\\\"nodes\\\":[{\\\"object\\\":\\\"block\\\",\\\"type\\\":\\\"list-item-child\\\",\\\"data\\\":{},\\\"nodes\\\":[{\\\"object\\\":\\\"text\\\",\\\"text\\\":\\\"Process Description\\\",\\\"marks\\\":[]},{\\\"object\\\":\\\"text\\\",\\\"text\\\":\\\" \\\",\\\"marks\\\":[{\\\"object\\\":\\\"mark\\\",\\\"type\\\":\\\"uui-richTextEditor-span-mark\\\",\\\"data\\\":{\\\"style\\\":{}}}]},{\\\"object\\\":\\\"text\\\",\\\"text\\\":\\\"/ Описание процесса- документ, описывающий набор взаимосвязанных или взаимодейтсвующих видов деятельности, которые используют входные данные для достижения намеченного результата и достижения целей процесса;\\\",\\\"marks\\\":[{\\\"object\\\":\\\"mark\\\",\\\"type\\\":\\\"uui-richTextEditor-span-mark\\\",\\\"data\\\":{\\\"style\\\":{}}}]}]}]},{\\\"object\\\":\\\"block\\\",\\\"type\\\":\\\"list-item\\\",\\\"data\\\":{},\\\"nodes\\\":[{\\\"object\\\":\\\"block\\\",\\\"type\\\":\\\"list-item-child\\\",\\\"data\\\":{},\\\"nodes\\\":[{\\\"object\\\":\\\"text\\\",\\\"text\\\":\\\"Procedure Description\\\",\\\"marks\\\":[]},{\\\"object\\\":\\\"text\\\",\\\"text\\\":\\\" \\\",\\\"marks\\\":[{\\\"object\\\":\\\"mark\\\",\\\"type\\\":\\\"uui-richTextEditor-span-mark\\\",\\\"data\\\":{\\\"style\\\":{}}}]},{\\\"object\\\":\\\"text\\\",\\\"text\\\":\\\"/ Описание процедуры- документ, описывающий определенный способ выполнения действия или процесса;\\\",\\\"marks\\\":[{\\\"object\\\":\\\"mark\\\",\\\"type\\\":\\\"uui-richTextEditor-span-mark\\\",\\\"data\\\":{\\\"style\\\":{}}}]}]}]},{\\\"object\\\":\\\"block\\\",\\\"type\\\":\\\"list-item\\\",\\\"data\\\":{},\\\"nodes\\\":[{\\\"object\\\":\\\"block\\\",\\\"type\\\":\\\"list-item-child\\\",\\\"data\\\":{},\\\"nodes\\\":[{\\\"object\\\":\\\"text\\\",\\\"text\\\":\\\"Work Instruction\\\",\\\"marks\\\":[]},{\\\"object\\\":\\\"text\\\",\\\"text\\\":\\\" \\\",\\\"marks\\\":[{\\\"object\\\":\\\"mark\\\",\\\"type\\\":\\\"uui-richTextEditor-span-mark\\\",\\\"data\\\":{\\\"style\\\":{}}}]},{\\\"object\\\":\\\"text\\\",\\\"text\\\":\\\"/ Рабочая инструкция- документ, содержащий подробное описание того, как выполнять и документировать задачи;\\\",\\\"marks\\\":[{\\\"object\\\":\\\"mark\\\",\\\"type\\\":\\\"uui-richTextEditor-span-mark\\\",\\\"data\\\":{\\\"style\\\":{}}}]}]}]},{\\\"object\\\":\\\"block\\\",\\\"type\\\":\\\"list-item\\\",\\\"data\\\":{},\\\"nodes\\\":[{\\\"object\\\":\\\"block\\\",\\\"type\\\":\\\"list-item-child\\\",\\\"data\\\":{},\\\"nodes\\\":[{\\\"object\\\":\\\"text\\\",\\\"text\\\":\\\"Guideline\\\",\\\"marks\\\":[]},{\\\"object\\\":\\\"text\\\",\\\"text\\\":\\\" \\\",\\\"marks\\\":[{\\\"object\\\":\\\"mark\\\",\\\"type\\\":\\\"uui-richTextEditor-span-mark\\\",\\\"data\\\":{\\\"style\\\":{}}}]},{\\\"object\\\":\\\"text\\\",\\\"text\\\":\\\"/ Руководство - документ, который предназначен для предоставления помощи, дополнения, руководства реализации нормативных актов\\\",\\\"marks\\\":[{\\\"object\\\":\\\"mark\\\",\\\"type\\\":\\\"uui-richTextEditor-span-mark\\\",\\\"data\\\":{\\\"style\\\":{}}}]},{\\\"object\\\":\\\"text\\\",\\\"text\\\":\\\" \\\",\\\"marks\\\":[{\\\"object\\\":\\\"mark\\\",\\\"type\\\":\\\"uui-richTextEditor-span-mark\\\",\\\"data\\\":{\\\"style\\\":{}}},{\\\"object\\\":\\\"mark\\\",\\\"type\\\":\\\"uui-richTextEditor-span-mark\\\",\\\"data\\\":{\\\"style\\\":{}}}]},{\\\"object\\\":\\\"text\\\",\\\"text\\\":\\\"EPAM;\\\",\\\"marks\\\":[]}]}]},{\\\"object\\\":\\\"block\\\",\\\"type\\\":\\\"list-item\\\",\\\"data\\\":{},\\\"nodes\\\":[{\\\"object\\\":\\\"block\\\",\\\"type\\\":\\\"list-item-child\\\",\\\"data\\\":{},\\\"nodes\\\":[{\\\"object\\\":\\\"text\\\",\\\"text\\\":\\\"Technical Specification / Техническая Спецификация - документ, содержащий подробный обзор базовых показателей безопасности EPAM для соответствующих активов;\\\",\\\"marks\\\":[]}]}]},{\\\"object\\\":\\\"block\\\",\\\"type\\\":\\\"list-item\\\",\\\"data\\\":{},\\\"nodes\\\":[{\\\"object\\\":\\\"block\\\",\\\"type\\\":\\\"list-item-child\\\",\\\"data\\\":{},\\\"nodes\\\":[{\\\"object\\\":\\\"text\\\",\\\"text\\\":\\\"Template\\\",\\\"marks\\\":[]},{\\\"object\\\":\\\"text\\\",\\\"text\\\":\\\" \\\",\\\"marks\\\":[{\\\"object\\\":\\\"mark\\\",\\\"type\\\":\\\"uui-richTextEditor-span-mark\\\",\\\"data\\\":{\\\"style\\\":{}}}]},{\\\"object\\\":\\\"text\\\",\\\"text\\\":\\\"/ Шаблон – Предопределенное содержание и формат артефакта;\\\",\\\"marks\\\":[{\\\"object\\\":\\\"mark\\\",\\\"type\\\":\\\"uui-richTextEditor-span-mark\\\",\\\"data\\\":{\\\"style\\\":{}}}]}]}]},{\\\"object\\\":\\\"block\\\",\\\"type\\\":\\\"list-item\\\",\\\"data\\\":{},\\\"nodes\\\":[{\\\"object\\\":\\\"block\\\",\\\"type\\\":\\\"list-item-child\\\",\\\"data\\\":{},\\\"nodes\\\":[{\\\"object\\\":\\\"text\\\",\\\"text\\\":\\\"Example\\\",\\\"marks\\\":[]},{\\\"object\\\":\\\"text\\\",\\\"text\\\":\\\" \\\",\\\"marks\\\":[{\\\"object\\\":\\\"mark\\\",\\\"type\\\":\\\"uui-richTextEditor-span-mark\\\",\\\"data\\\":{\\\"style\\\":{}}}]},{\\\"object\\\":\\\"text\\\",\\\"text\\\":\\\"/ Образец - документ, содержащий рекомендации и лучшие практики по написанию артефакта в соответствии с его предопределенным шаблоном и уровнем информации, подлежащей заполнению.\\\",\\\"marks\\\":[{\\\"object\\\":\\\"mark\\\",\\\"type\\\":\\\"uui-richTextEditor-span-mark\\\",\\\"data\\\":{\\\"style\\\":{}}}]}]}]}]}]},{\\\"object\\\":\\\"block\\\",\\\"type\\\":\\\"list-item\\\",\\\"data\\\":{},\\\"nodes\\\":[{\\\"object\\\":\\\"block\\\",\\\"type\\\":\\\"list-item-child\\\",\\\"data\\\":{},\\\"nodes\\\":[{\\\"object\\\":\\\"text\\\",\\\"text\\\":\\\"Проектные артефакты\\\",\\\"marks\\\":[{\\\"object\\\":\\\"mark\\\",\\\"type\\\":\\\"uui-richTextEditor-bold\\\",\\\"data\\\":{}}]},{\\\"object\\\":\\\"text\\\",\\\"text\\\":\\\" \\\",\\\"marks\\\":[{\\\"object\\\":\\\"mark\\\",\\\"type\\\":\\\"uui-richTextEditor-span-mark\\\",\\\"data\\\":{\\\"style\\\":{}}}]},{\\\"object\\\":\\\"text\\\",\\\"text\\\":\\\"включают в себя документы и записи, разработанные проектами EPAM.\\\",\\\"marks\\\":[]}]}]},{\\\"object\\\":\\\"block\\\",\\\"type\\\":\\\"list-item\\\",\\\"data\\\":{},\\\"nodes\\\":[{\\\"object\\\":\\\"block\\\",\\\"type\\\":\\\"list-item-child\\\",\\\"data\\\":{},\\\"nodes\\\":[{\\\"object\\\":\\\"text\\\",\\\"text\\\":\\\"Организационные артефакты\\\",\\\"marks\\\":[{\\\"object\\\":\\\"mark\\\",\\\"type\\\":\\\"uui-richTextEditor-bold\\\",\\\"data\\\":{}}]},{\\\"object\\\":\\\"text\\\",\\\"text\\\":\\\" \\\",\\\"marks\\\":[{\\\"object\\\":\\\"mark\\\",\\\"type\\\":\\\"uui-richTextEditor-span-mark\\\",\\\"data\\\":{\\\"style\\\":{}}}]},{\\\"object\\\":\\\"text\\\",\\\"text\\\":\\\"включают в себя документы и записи, разработанные службами EPAM и предназначенные для их использования.\\\",\\\"marks\\\":[]}]}]}]},{\\\"object\\\":\\\"block\\\",\\\"type\\\":\\\"paragraph\\\",\\\"data\\\":{},\\\"nodes\\\":[{\\\"object\\\":\\\"text\\\",\\\"text\\\":\\\"Секция “External normative documents”, вкладка PAL, содержит информацию о том как получить необходимый для вашей работы артефакт внешнего происхождения (например, стандарт).\\\",\\\"marks\\\":[]}]},{\\\"object\\\":\\\"block\\\",\\\"type\\\":\\\"paragraph\\\",\\\"data\\\":{},\\\"nodes\\\":[{\\\"object\\\":\\\"text\\\",\\\"text\\\":\\\"Больше информации об управлениии артефактами внешнего происхождения можно найти в\\\",\\\"marks\\\":[]},{\\\"object\\\":\\\"text\\\",\\\"text\\\":\\\" \\\",\\\"marks\\\":[{\\\"object\\\":\\\"mark\\\",\\\"type\\\":\\\"uui-richTextEditor-span-mark\\\",\\\"data\\\":{\\\"style\\\":{}}}]},{\\\"object\\\":\\\"inline\\\",\\\"type\\\":\\\"link\\\",\\\"data\\\":{\\\"url\\\":\\\"https://pal.epam.com/pal_method_plugin/guidances/whitepapers/doc_PD_ArtifactManagementforExternalOriginArtifactsProcedure_5E67E3BE.html\\\"},\\\"nodes\\\":[{\\\"object\\\":\\\"text\\\",\\\"text\\\":\\\"Artifact Management for External Origin Artifacts Procedure Description\\\",\\\"marks\\\":[]}]},{\\\"object\\\":\\\"text\\\",\\\"text\\\":\\\".\\\",\\\"marks\\\":[]}]},{\\\"object\\\":\\\"block\\\",\\\"type\\\":\\\"image\\\",\\\"data\\\":{\\\"src\\\":\\\"https://onboarding.epam.com/app/cdn/55143803-c7ee-48ea-9ae5-c3c0943d3a38/1.png\\\",\\\"imageSize\\\":{\\\"width\\\":781,\\\"height\\\":348}},\\\"nodes\\\":[{\\\"object\\\":\\\"text\\\",\\\"text\\\":\\\"\\\",\\\"marks\\\":[]}]},{\\\"object\\\":\\\"block\\\",\\\"type\\\":\\\"paragraph\\\",\\\"data\\\":{},\\\"nodes\\\":[{\\\"object\\\":\\\"text\\\",\\\"text\\\":\\\"\\\\n\\\",\\\"marks\\\":[{\\\"object\\\":\\\"mark\\\",\\\"type\\\":\\\"uui-richTextEditor-bold\\\",\\\"data\\\":{}}]}]},{\\\"object\\\":\\\"block\\\",\\\"type\\\":\\\"paragraph\\\",\\\"data\\\":{},\\\"nodes\\\":[{\\\"object\\\":\\\"text\\\",\\\"text\\\":\\\"Секция “ International Certifications”, вкладка PAL, содержит информацию обо всех имеющихся сертификатах по локациям. Также на данной вкладке имеется интерактивная карта, показывающая офисы EPAM, сертифицированные в соответствии с различными требованиями стандартов.\\\",\\\"marks\\\":[]}]},{\\\"object\\\":\\\"block\\\",\\\"type\\\":\\\"image\\\",\\\"data\\\":{\\\"src\\\":\\\"https://onboarding.epam.com/app/cdn/181c8e66-d7f1-4c7e-9384-370d52549c63/2.png\\\",\\\"imageSize\\\":{\\\"width\\\":1029,\\\"height\\\":612}},\\\"nodes\\\":[{\\\"object\\\":\\\"text\\\",\\\"text\\\":\\\"\\\",\\\"marks\\\":[]}]},{\\\"object\\\":\\\"block\\\",\\\"type\\\":\\\"paragraph\\\",\\\"data\\\":{},\\\"nodes\\\":[{\\\"object\\\":\\\"text\\\",\\\"text\\\":\\\"Нормативные акты EPAM\\\",\\\"marks\\\":[]},{\\\"object\\\":\\\"text\\\",\\\"text\\\":\\\" \\\",\\\"marks\\\":[{\\\"object\\\":\\\"mark\\\",\\\"type\\\":\\\"uui-richTextEditor-span-mark\\\",\\\"data\\\":{\\\"style\\\":{}}}]},{\\\"object\\\":\\\"text\\\",\\\"text\\\":\\\"представлены в соответствующих секциях\\\",\\\"marks\\\":[{\\\"object\\\":\\\"mark\\\",\\\"type\\\":\\\"uui-richTextEditor-span-mark\\\",\\\"data\\\":{\\\"style\\\":{}}}]},{\\\"object\\\":\\\"text\\\",\\\"text\\\":\\\" \\\",\\\"marks\\\":[{\\\"object\\\":\\\"mark\\\",\\\"type\\\":\\\"uui-richTextEditor-span-mark\\\",\\\"data\\\":{\\\"style\\\":{}}},{\\\"object\\\":\\\"mark\\\",\\\"type\\\":\\\"uui-richTextEditor-span-mark\\\",\\\"data\\\":{\\\"style\\\":{}}}]},{\\\"object\\\":\\\"text\\\",\\\"text\\\":\\\"PAL и вкладке «EPAM Regulations».\\\",\\\"marks\\\":[]}]},{\\\"object\\\":\\\"block\\\",\\\"type\\\":\\\"paragraph\\\",\\\"data\\\":{},\\\"nodes\\\":[{\\\"object\\\":\\\"text\\\",\\\"text\\\":\\\"Иерархическая структура артифактов может быть представлена следующим образом:\\\",\\\"marks\\\":[]}]},{\\\"object\\\":\\\"block\\\",\\\"type\\\":\\\"paragraph\\\",\\\"data\\\":{},\\\"nodes\\\":[{\\\"object\\\":\\\"text\\\",\\\"text\\\":\\\"\\\\n\\\",\\\"marks\\\":[]}]},{\\\"object\\\":\\\"block\\\",\\\"type\\\":\\\"image\\\",\\\"data\\\":{\\\"src\\\":\\\"https://onboarding.epam.com/app/cdn/e0ede8a5-1256-454b-8922-33335476431b/Drawing1.jpg\\\",\\\"imageSize\\\":{\\\"width\\\":1011,\\\"height\\\":731}},\\\"nodes\\\":[{\\\"object\\\":\\\"text\\\",\\\"text\\\":\\\"\\\",\\\"marks\\\":[]}]},{\\\"object\\\":\\\"block\\\",\\\"type\\\":\\\"paragraph\\\",\\\"data\\\":{},\\\"nodes\\\":[{\\\"object\\\":\\\"text\\\",\\\"text\\\":\\\"Уровень 1-3\\\",\\\"marks\\\":[{\\\"object\\\":\\\"mark\\\",\\\"type\\\":\\\"uui-richTextEditor-bold\\\",\\\"data\\\":{}}]},{\\\"object\\\":\\\"text\\\",\\\"text\\\":\\\" Артефакты хранятся в \\\",\\\"marks\\\":[]},{\\\"object\\\":\\\"inline\\\",\\\"type\\\":\\\"link\\\",\\\"data\\\":{\\\"url\\\":\\\"https://pal.epam.com/\\\"},\\\"nodes\\\":[{\\\"object\\\":\\\"text\\\",\\\"text\\\":\\\"EPAM PAL\\\",\\\"marks\\\":[]}]},{\\\"object\\\":\\\"text\\\",\\\"text\\\":\\\"\\\",\\\"marks\\\":[]}]},{\\\"object\\\":\\\"block\\\",\\\"type\\\":\\\"paragraph\\\",\\\"data\\\":{},\\\"nodes\\\":[{\\\"object\\\":\\\"text\\\",\\\"text\\\":\\\"Уровень 4\\\",\\\"marks\\\":[{\\\"object\\\":\\\"mark\\\",\\\"type\\\":\\\"uui-richTextEditor-bold\\\",\\\"data\\\":{}}]},{\\\"object\\\":\\\"text\\\",\\\"text\\\":\\\" Документация находится под управлением соответствующих руководителей проектов, подразделений, сервисов и хранится в соответствующих системах, в которых ведутся данные активности.\\\",\\\"marks\\\":[]}]},{\\\"object\\\":\\\"block\\\",\\\"type\\\":\\\"paragraph\\\",\\\"data\\\":{},\\\"nodes\\\":[{\\\"object\\\":\\\"text\\\",\\\"text\\\":\\\"Документы в PAL доступны всем сотрудникам.\\\",\\\"marks\\\":[]}]},{\\\"object\\\":\\\"block\\\",\\\"type\\\":\\\"paragraph\\\",\\\"data\\\":{},\\\"nodes\\\":[{\\\"object\\\":\\\"text\\\",\\\"text\\\":\\\"\\\\n\\\",\\\"marks\\\":[]}]},{\\\"object\\\":\\\"block\\\",\\\"type\\\":\\\"paragraph\\\",\\\"data\\\":{},\\\"nodes\\\":[{\\\"object\\\":\\\"text\\\",\\\"text\\\":\\\"Если у вас возникли вопросы, касающиеся данного раздела, пожалуйста, обратитесь к вашему Менеджеру или Персональному Ассистенту, либо свяжитесь с нами через \\\",\\\"marks\\\":[]},{\\\"object\\\":\\\"inline\\\",\\\"type\\\":\\\"link\\\",\\\"data\\\":{\\\"url\\\":\\\"https://support.epam.com/esp/ess.do?orderitem=caQMSSupportRequestsTrainingSupportRequest#complete\\\"},\\\"nodes\\\":[{\\\"object\\\":\\\"text\\\",\\\"text\\\":\\\"QMS Training Support\\\",\\\"marks\\\":[]}]},{\\\"object\\\":\\\"text\\\",\\\"text\\\":\\\".\\\",\\\"marks\\\":[]}]},{\\\"object\\\":\\\"block\\\",\\\"type\\\":\\\"paragraph\\\",\\\"data\\\":{},\\\"nodes\\\":[{\\\"object\\\":\\\"text\\\",\\\"text\\\":\\\"\\\\n\\\\n\\\",\\\"marks\\\":[]}]}]}}\""}