{"content":"\"{\\\"object\\\":\\\"value\\\",\\\"document\\\":{\\\"object\\\":\\\"document\\\",\\\"data\\\":{},\\\"nodes\\\":[{\\\"object\\\":\\\"block\\\",\\\"type\\\":\\\"paragraph\\\",\\\"data\\\":{},\\\"nodes\\\":[{\\\"object\\\":\\\"text\\\",\\\"text\\\":\\\"During more than 10 years of collaboration TR CBU gathered a lot of useful information. The \\\",\\\"marks\\\":[]},{\\\"object\\\":\\\"inline\\\",\\\"type\\\":\\\"link\\\",\\\"data\\\":{\\\"url\\\":\\\"https://kb.epam.com/display/TRI/\\\"},\\\"nodes\\\":[{\\\"object\\\":\\\"text\\\",\\\"text\\\":\\\"Knowledge Base\\\",\\\"marks\\\":[{\\\"object\\\":\\\"mark\\\",\\\"type\\\":\\\"uui-richTextEditor-span-mark\\\",\\\"data\\\":{\\\"style\\\":{\\\"text-decoration\\\":\\\"underline\\\"}}},{\\\"object\\\":\\\"mark\\\",\\\"type\\\":\\\"uui-richTextEditor-span-mark\\\",\\\"data\\\":{\\\"style\\\":{}}}]}]},{\\\"object\\\":\\\"text\\\",\\\"text\\\":\\\" covers the following topics:\\\",\\\"marks\\\":[]}]},{\\\"object\\\":\\\"block\\\",\\\"type\\\":\\\"paragraph\\\",\\\"data\\\":{},\\\"nodes\\\":[{\\\"object\\\":\\\"text\\\",\\\"text\\\":\\\"Competencies\\\",\\\"marks\\\":[{\\\"object\\\":\\\"mark\\\",\\\"type\\\":\\\"uui-richTextEditor-bold\\\",\\\"data\\\":{}}]}]},{\\\"object\\\":\\\"block\\\",\\\"type\\\":\\\"unordered-list\\\",\\\"data\\\":{},\\\"nodes\\\":[{\\\"object\\\":\\\"block\\\",\\\"type\\\":\\\"list-item\\\",\\\"data\\\":{},\\\"nodes\\\":[{\\\"object\\\":\\\"block\\\",\\\"type\\\":\\\"list-item-child\\\",\\\"data\\\":{},\\\"nodes\\\":[{\\\"object\\\":\\\"text\\\",\\\"text\\\":\\\"\\\",\\\"marks\\\":[]},{\\\"object\\\":\\\"inline\\\",\\\"type\\\":\\\"link\\\",\\\"data\\\":{\\\"url\\\":\\\"https://kb.epam.com/display/TRI/Business+Domain\\\"},\\\"nodes\\\":[{\\\"object\\\":\\\"text\\\",\\\"text\\\":\\\"Business Domain\\\",\\\"marks\\\":[]}]},{\\\"object\\\":\\\"text\\\",\\\"text\\\":\\\"\\\",\\\"marks\\\":[]}]}]},{\\\"object\\\":\\\"block\\\",\\\"type\\\":\\\"list-item\\\",\\\"data\\\":{},\\\"nodes\\\":[{\\\"object\\\":\\\"block\\\",\\\"type\\\":\\\"list-item-child\\\",\\\"data\\\":{},\\\"nodes\\\":[{\\\"object\\\":\\\"text\\\",\\\"text\\\":\\\"\\\",\\\"marks\\\":[]},{\\\"object\\\":\\\"inline\\\",\\\"type\\\":\\\"link\\\",\\\"data\\\":{\\\"url\\\":\\\"https://kb.epam.com/display/TRI/Technology+Practices\\\"},\\\"nodes\\\":[{\\\"object\\\":\\\"text\\\",\\\"text\\\":\\\"Technology Practices\\\",\\\"marks\\\":[]}]},{\\\"object\\\":\\\"text\\\",\\\"text\\\":\\\"\\\",\\\"marks\\\":[]}]}]}]},{\\\"object\\\":\\\"block\\\",\\\"type\\\":\\\"paragraph\\\",\\\"data\\\":{},\\\"nodes\\\":[{\\\"object\\\":\\\"text\\\",\\\"text\\\":\\\"Practical Information\\\",\\\"marks\\\":[{\\\"object\\\":\\\"mark\\\",\\\"type\\\":\\\"uui-richTextEditor-bold\\\",\\\"data\\\":{}}]}]},{\\\"object\\\":\\\"block\\\",\\\"type\\\":\\\"unordered-list\\\",\\\"data\\\":{},\\\"nodes\\\":[{\\\"object\\\":\\\"block\\\",\\\"type\\\":\\\"list-item\\\",\\\"data\\\":{},\\\"nodes\\\":[{\\\"object\\\":\\\"block\\\",\\\"type\\\":\\\"list-item-child\\\",\\\"data\\\":{},\\\"nodes\\\":[{\\\"object\\\":\\\"text\\\",\\\"text\\\":\\\"\\\",\\\"marks\\\":[]},{\\\"object\\\":\\\"inline\\\",\\\"type\\\":\\\"link\\\",\\\"data\\\":{\\\"url\\\":\\\"https://kb.epam.com/pages/viewpage.action?pageId=233605018\\\"},\\\"nodes\\\":[{\\\"object\\\":\\\"text\\\",\\\"text\\\":\\\"F.A.Q.\\\",\\\"marks\\\":[]}]},{\\\"object\\\":\\\"text\\\",\\\"text\\\":\\\"\\\",\\\"marks\\\":[]}]}]},{\\\"object\\\":\\\"block\\\",\\\"type\\\":\\\"list-item\\\",\\\"data\\\":{},\\\"nodes\\\":[{\\\"object\\\":\\\"block\\\",\\\"type\\\":\\\"list-item-child\\\",\\\"data\\\":{},\\\"nodes\\\":[{\\\"object\\\":\\\"text\\\",\\\"text\\\":\\\"\\\",\\\"marks\\\":[]},{\\\"object\\\":\\\"inline\\\",\\\"type\\\":\\\"link\\\",\\\"data\\\":{\\\"url\\\":\\\"https://kb.epam.com/display/TRI/Working+Environment\\\"},\\\"nodes\\\":[{\\\"object\\\":\\\"text\\\",\\\"text\\\":\\\"Working Environment\\\",\\\"marks\\\":[]}]},{\\\"object\\\":\\\"text\\\",\\\"text\\\":\\\"\\\",\\\"marks\\\":[]}]}]}]},{\\\"object\\\":\\\"block\\\",\\\"type\\\":\\\"paragraph\\\",\\\"data\\\":{},\\\"nodes\\\":[{\\\"object\\\":\\\"text\\\",\\\"text\\\":\\\"Programs\\\",\\\"marks\\\":[{\\\"object\\\":\\\"mark\\\",\\\"type\\\":\\\"uui-richTextEditor-bold\\\",\\\"data\\\":{}}]}]},{\\\"object\\\":\\\"block\\\",\\\"type\\\":\\\"unordered-list\\\",\\\"data\\\":{},\\\"nodes\\\":[{\\\"object\\\":\\\"block\\\",\\\"type\\\":\\\"list-item\\\",\\\"data\\\":{},\\\"nodes\\\":[{\\\"object\\\":\\\"block\\\",\\\"type\\\":\\\"list-item-child\\\",\\\"data\\\":{},\\\"nodes\\\":[{\\\"object\\\":\\\"text\\\",\\\"text\\\":\\\"\\\",\\\"marks\\\":[]},{\\\"object\\\":\\\"inline\\\",\\\"type\\\":\\\"link\\\",\\\"data\\\":{\\\"url\\\":\\\"https://kb.epam.com/display/TRI/HR+Programs\\\"},\\\"nodes\\\":[{\\\"object\\\":\\\"text\\\",\\\"text\\\":\\\"HR Programs\\\",\\\"marks\\\":[]}]},{\\\"object\\\":\\\"text\\\",\\\"text\\\":\\\"\\\",\\\"marks\\\":[]}]}]},{\\\"object\\\":\\\"block\\\",\\\"type\\\":\\\"list-item\\\",\\\"data\\\":{},\\\"nodes\\\":[{\\\"object\\\":\\\"block\\\",\\\"type\\\":\\\"list-item-child\\\",\\\"data\\\":{},\\\"nodes\\\":[{\\\"object\\\":\\\"text\\\",\\\"text\\\":\\\"\\\",\\\"marks\\\":[]},{\\\"object\\\":\\\"inline\\\",\\\"type\\\":\\\"link\\\",\\\"data\\\":{\\\"url\\\":\\\"https://kb.epam.com/display/TRI/Innovations\\\"},\\\"nodes\\\":[{\\\"object\\\":\\\"text\\\",\\\"text\\\":\\\"Innovations\\\",\\\"marks\\\":[]}]},{\\\"object\\\":\\\"text\\\",\\\"text\\\":\\\"\\\",\\\"marks\\\":[]}]}]}]},{\\\"object\\\":\\\"block\\\",\\\"type\\\":\\\"paragraph\\\",\\\"data\\\":{},\\\"nodes\\\":[{\\\"object\\\":\\\"text\\\",\\\"text\\\":\\\"Thomson Reuters\\\",\\\"marks\\\":[{\\\"object\\\":\\\"mark\\\",\\\"type\\\":\\\"uui-richTextEditor-bold\\\",\\\"data\\\":{}}]}]},{\\\"object\\\":\\\"block\\\",\\\"type\\\":\\\"unordered-list\\\",\\\"data\\\":{},\\\"nodes\\\":[{\\\"object\\\":\\\"block\\\",\\\"type\\\":\\\"list-item\\\",\\\"data\\\":{},\\\"nodes\\\":[{\\\"object\\\":\\\"block\\\",\\\"type\\\":\\\"list-item-child\\\",\\\"data\\\":{},\\\"nodes\\\":[{\\\"object\\\":\\\"text\\\",\\\"text\\\":\\\"\\\",\\\"marks\\\":[]},{\\\"object\\\":\\\"inline\\\",\\\"type\\\":\\\"link\\\",\\\"data\\\":{\\\"url\\\":\\\"https://kb.epam.com/display/TRI/Projects\\\"},\\\"nodes\\\":[{\\\"object\\\":\\\"text\\\",\\\"text\\\":\\\"Projects\\\",\\\"marks\\\":[]}]},{\\\"object\\\":\\\"text\\\",\\\"text\\\":\\\"\\\",\\\"marks\\\":[]}]}]},{\\\"object\\\":\\\"block\\\",\\\"type\\\":\\\"list-item\\\",\\\"data\\\":{},\\\"nodes\\\":[{\\\"object\\\":\\\"block\\\",\\\"type\\\":\\\"list-item-child\\\",\\\"data\\\":{},\\\"nodes\\\":[{\\\"object\\\":\\\"text\\\",\\\"text\\\":\\\"\\\",\\\"marks\\\":[]},{\\\"object\\\":\\\"inline\\\",\\\"type\\\":\\\"link\\\",\\\"data\\\":{\\\"url\\\":\\\"https://kb.epam.com/display/TRI/Solutions\\\"},\\\"nodes\\\":[{\\\"object\\\":\\\"text\\\",\\\"text\\\":\\\"Solutions\\\",\\\"marks\\\":[]}]},{\\\"object\\\":\\\"text\\\",\\\"text\\\":\\\"\\\",\\\"marks\\\":[]}]}]}]},{\\\"object\\\":\\\"block\\\",\\\"type\\\":\\\"paragraph\\\",\\\"data\\\":{},\\\"nodes\\\":[{\\\"object\\\":\\\"text\\\",\\\"text\\\":\\\" \\\",\\\"marks\\\":[]}]},{\\\"object\\\":\\\"block\\\",\\\"type\\\":\\\"paragraph\\\",\\\"data\\\":{},\\\"nodes\\\":[{\\\"object\\\":\\\"text\\\",\\\"text\\\":\\\"\\\\n\\\\n\\\",\\\"marks\\\":[]}]}]}}\""}