{"content":"\"{\\\"object\\\":\\\"value\\\",\\\"document\\\":{\\\"object\\\":\\\"document\\\",\\\"data\\\":{},\\\"nodes\\\":[{\\\"object\\\":\\\"block\\\",\\\"type\\\":\\\"paragraph\\\",\\\"data\\\":{},\\\"nodes\\\":[{\\\"object\\\":\\\"text\\\",\\\"text\\\":\\\"The Exit Management Process \\\",\\\"marks\\\":[{\\\"object\\\":\\\"mark\\\",\\\"type\\\":\\\"uui-richTextEditor-bold\\\",\\\"data\\\":{}}]},{\\\"object\\\":\\\"text\\\",\\\"text\\\":\\\"is the internal Company process pertaining to departing Employees and outlines a number of actions to make the departure smooth, ensures that the Employee receives final payments and documents, and the overall experience is a positive one. You, as a Resource Manager, play a vital role in ensuring that this is done in a timely and respectful manner.\\\",\\\"marks\\\":[]}]},{\\\"object\\\":\\\"block\\\",\\\"type\\\":\\\"paragraph\\\",\\\"data\\\":{},\\\"nodes\\\":[{\\\"object\\\":\\\"text\\\",\\\"text\\\":\\\"There are two types of terminations:\\\",\\\"marks\\\":[]}]},{\\\"object\\\":\\\"block\\\",\\\"type\\\":\\\"unordered-list\\\",\\\"data\\\":{},\\\"nodes\\\":[{\\\"object\\\":\\\"block\\\",\\\"type\\\":\\\"list-item\\\",\\\"data\\\":{},\\\"nodes\\\":[{\\\"object\\\":\\\"block\\\",\\\"type\\\":\\\"list-item-child\\\",\\\"data\\\":{},\\\"nodes\\\":[{\\\"object\\\":\\\"text\\\",\\\"text\\\":\\\"Voluntary \\\",\\\"marks\\\":[{\\\"object\\\":\\\"mark\\\",\\\"type\\\":\\\"uui-richTextEditor-bold\\\",\\\"data\\\":{}}]},{\\\"object\\\":\\\"text\\\",\\\"text\\\":\\\"(initiated by Employee)\\\",\\\"marks\\\":[]}]}]},{\\\"object\\\":\\\"block\\\",\\\"type\\\":\\\"list-item\\\",\\\"data\\\":{},\\\"nodes\\\":[{\\\"object\\\":\\\"block\\\",\\\"type\\\":\\\"list-item-child\\\",\\\"data\\\":{},\\\"nodes\\\":[{\\\"object\\\":\\\"text\\\",\\\"text\\\":\\\"Involuntary \\\",\\\"marks\\\":[{\\\"object\\\":\\\"mark\\\",\\\"type\\\":\\\"uui-richTextEditor-bold\\\",\\\"data\\\":{}}]},{\\\"object\\\":\\\"text\\\",\\\"text\\\":\\\"(initiated by the Company)\\\",\\\"marks\\\":[]}]}]}]},{\\\"object\\\":\\\"block\\\",\\\"type\\\":\\\"paragraph\\\",\\\"data\\\":{},\\\"nodes\\\":[{\\\"object\\\":\\\"text\\\",\\\"text\\\":\\\"Below are step-by-step instructions to follow for exiting Employees.\\\",\\\"marks\\\":[]}]},{\\\"object\\\":\\\"block\\\",\\\"type\\\":\\\"uui-richTextEditor-header-3\\\",\\\"data\\\":{},\\\"nodes\\\":[{\\\"object\\\":\\\"text\\\",\\\"text\\\":\\\"In case of voluntary termination:\\\",\\\"marks\\\":[]}]},{\\\"object\\\":\\\"block\\\",\\\"type\\\":\\\"unordered-list\\\",\\\"data\\\":{},\\\"nodes\\\":[{\\\"object\\\":\\\"block\\\",\\\"type\\\":\\\"list-item\\\",\\\"data\\\":{},\\\"nodes\\\":[{\\\"object\\\":\\\"block\\\",\\\"type\\\":\\\"list-item-child\\\",\\\"data\\\":{},\\\"nodes\\\":[{\\\"object\\\":\\\"text\\\",\\\"text\\\":\\\"Inform your Upper Manager/Reporter and People Management Team about the situation. The People Partner will provide guidance for the preparation of the dismissal as well as during the meeting\\\",\\\"marks\\\":[]}]}]},{\\\"object\\\":\\\"block\\\",\\\"type\\\":\\\"list-item\\\",\\\"data\\\":{},\\\"nodes\\\":[{\\\"object\\\":\\\"block\\\",\\\"type\\\":\\\"list-item-child\\\",\\\"data\\\":{},\\\"nodes\\\":[{\\\"object\\\":\\\"text\\\",\\\"text\\\":\\\"Have a conversation with your Employee to find out the reasons for leaving and if necessary, possible ways to retain the Employee\\\",\\\"marks\\\":[]}]}]},{\\\"object\\\":\\\"block\\\",\\\"type\\\":\\\"list-item\\\",\\\"data\\\":{},\\\"nodes\\\":[{\\\"object\\\":\\\"block\\\",\\\"type\\\":\\\"list-item-child\\\",\\\"data\\\":{},\\\"nodes\\\":[{\\\"object\\\":\\\"text\\\",\\\"text\\\":\\\"Research with your People Partner/HR Contact all possible options to retain the employee in the company if appropriate\\\",\\\"marks\\\":[]}]}]},{\\\"object\\\":\\\"block\\\",\\\"type\\\":\\\"list-item\\\",\\\"data\\\":{},\\\"nodes\\\":[{\\\"object\\\":\\\"block\\\",\\\"type\\\":\\\"list-item-child\\\",\\\"data\\\":{},\\\"nodes\\\":[{\\\"object\\\":\\\"text\\\",\\\"text\\\":\\\"If all options have been discussed with the Employee and they still plan to leave the Company, discuss the terms and the last working day with EPAM\\\",\\\"marks\\\":[]}]}]},{\\\"object\\\":\\\"block\\\",\\\"type\\\":\\\"list-item\\\",\\\"data\\\":{},\\\"nodes\\\":[{\\\"object\\\":\\\"block\\\",\\\"type\\\":\\\"list-item-child\\\",\\\"data\\\":{},\\\"nodes\\\":[{\\\"object\\\":\\\"text\\\",\\\"text\\\":\\\"Create an Exit Request in UPSA \\\",\\\"marks\\\":[]},{\\\"object\\\":\\\"text\\\",\\\"text\\\":\\\"at least 10 working days before\\\",\\\"marks\\\":[{\\\"object\\\":\\\"mark\\\",\\\"type\\\":\\\"uui-richTextEditor-bold\\\",\\\"data\\\":{}}]},{\\\"object\\\":\\\"text\\\",\\\"text\\\":\\\" the last working date\\\",\\\"marks\\\":[]},{\\\"object\\\":\\\"text\\\",\\\"text\\\":\\\" \\\",\\\"marks\\\":[{\\\"object\\\":\\\"mark\\\",\\\"type\\\":\\\"uui-richTextEditor-bold\\\",\\\"data\\\":{}}]},{\\\"object\\\":\\\"text\\\",\\\"text\\\":\\\" (Can be done by the People Team, if applicable)\\\",\\\"marks\\\":[]}]}]},{\\\"object\\\":\\\"block\\\",\\\"type\\\":\\\"list-item\\\",\\\"data\\\":{},\\\"nodes\\\":[{\\\"object\\\":\\\"block\\\",\\\"type\\\":\\\"list-item-child\\\",\\\"data\\\":{},\\\"nodes\\\":[{\\\"object\\\":\\\"text\\\",\\\"text\\\":\\\"Work with the Account/Project Leadership around notifying the client and identifying backfill options\\\",\\\"marks\\\":[]}]}]}]},{\\\"object\\\":\\\"block\\\",\\\"type\\\":\\\"uui-richTextEditor-header-3\\\",\\\"data\\\":{},\\\"nodes\\\":[{\\\"object\\\":\\\"text\\\",\\\"text\\\":\\\"In case of involuntary termination:\\\",\\\"marks\\\":[]}]},{\\\"object\\\":\\\"block\\\",\\\"type\\\":\\\"unordered-list\\\",\\\"data\\\":{},\\\"nodes\\\":[{\\\"object\\\":\\\"block\\\",\\\"type\\\":\\\"list-item\\\",\\\"data\\\":{},\\\"nodes\\\":[{\\\"object\\\":\\\"block\\\",\\\"type\\\":\\\"list-item-child\\\",\\\"data\\\":{},\\\"nodes\\\":[{\\\"object\\\":\\\"text\\\",\\\"text\\\":\\\"Inform your Upper Manager/Reporter and People Management Team about the situation\\\",\\\"marks\\\":[]}]}]},{\\\"object\\\":\\\"block\\\",\\\"type\\\":\\\"list-item\\\",\\\"data\\\":{},\\\"nodes\\\":[{\\\"object\\\":\\\"block\\\",\\\"type\\\":\\\"list-item-child\\\",\\\"data\\\":{},\\\"nodes\\\":[{\\\"object\\\":\\\"text\\\",\\\"text\\\":\\\"Conduct a discussion with the Employee that is focused on ensuring that the Employee leaves with a clear understanding of the reason for the exit and feeling that they have been treated with respect\\\",\\\"marks\\\":[]}]}]},{\\\"object\\\":\\\"block\\\",\\\"type\\\":\\\"list-item\\\",\\\"data\\\":{},\\\"nodes\\\":[{\\\"object\\\":\\\"block\\\",\\\"type\\\":\\\"list-item-child\\\",\\\"data\\\":{},\\\"nodes\\\":[{\\\"object\\\":\\\"text\\\",\\\"text\\\":\\\"Discuss the terms and the last working day in EPAM for the employee\\\",\\\"marks\\\":[]}]}]},{\\\"object\\\":\\\"block\\\",\\\"type\\\":\\\"list-item\\\",\\\"data\\\":{},\\\"nodes\\\":[{\\\"object\\\":\\\"block\\\",\\\"type\\\":\\\"list-item-child\\\",\\\"data\\\":{},\\\"nodes\\\":[{\\\"object\\\":\\\"text\\\",\\\"text\\\":\\\"Ensure that Company exit policy is followed - create an Exit Request in UPSA\\\",\\\"marks\\\":[]},{\\\"object\\\":\\\"text\\\",\\\"text\\\":\\\" at least 10 working days before\\\",\\\"marks\\\":[{\\\"object\\\":\\\"mark\\\",\\\"type\\\":\\\"uui-richTextEditor-bold\\\",\\\"data\\\":{}}]},{\\\"object\\\":\\\"text\\\",\\\"text\\\":\\\" the desired termination date\\\",\\\"marks\\\":[]}]}]}]},{\\\"object\\\":\\\"block\\\",\\\"type\\\":\\\"uui-richTextEditor-quote\\\",\\\"data\\\":{},\\\"nodes\\\":[{\\\"object\\\":\\\"block\\\",\\\"type\\\":\\\"paragraph\\\",\\\"data\\\":{},\\\"nodes\\\":[{\\\"object\\\":\\\"text\\\",\\\"text\\\":\\\"NB: In both cases the Exit Interview is conducted by People Partner/HR Contact (apart from several countries: USA, Canada and Mexico and Ukraine).\\\",\\\"marks\\\":[]}]}]},{\\\"object\\\":\\\"block\\\",\\\"type\\\":\\\"paragraph\\\",\\\"data\\\":{},\\\"nodes\\\":[{\\\"object\\\":\\\"text\\\",\\\"text\\\":\\\"The main purpose of the exit interview is to discover/assess the issues or reasons that made the employee decide to leave the company. It is also used as an instrument to allow departing employees to have a voice about what their work experience was like; to receive valuable feedback on what needs to be improved and leave on a positive note, with good relations, mutual respect.\\\",\\\"marks\\\":[]}]},{\\\"object\\\":\\\"block\\\",\\\"type\\\":\\\"uui-richTextEditor-header-2\\\",\\\"data\\\":{},\\\"nodes\\\":[{\\\"object\\\":\\\"text\\\",\\\"text\\\":\\\"STEP 1. Create an exit request in UPSA:\\\",\\\"marks\\\":[]}]},{\\\"object\\\":\\\"block\\\",\\\"type\\\":\\\"paragraph\\\",\\\"data\\\":{},\\\"nodes\\\":[{\\\"object\\\":\\\"text\\\",\\\"text\\\":\\\"This step can be done by the People Team, if applicable. \\\",\\\"marks\\\":[]}]},{\\\"object\\\":\\\"block\\\",\\\"type\\\":\\\"paragraph\\\",\\\"data\\\":{},\\\"nodes\\\":[{\\\"object\\\":\\\"text\\\",\\\"text\\\":\\\"The Exit Request in UPSA can be created in several ways:\\\",\\\"marks\\\":[]}]},{\\\"object\\\":\\\"block\\\",\\\"type\\\":\\\"unordered-list\\\",\\\"data\\\":{},\\\"nodes\\\":[{\\\"object\\\":\\\"block\\\",\\\"type\\\":\\\"list-item\\\",\\\"data\\\":{},\\\"nodes\\\":[{\\\"object\\\":\\\"block\\\",\\\"type\\\":\\\"list-item-child\\\",\\\"data\\\":{},\\\"nodes\\\":[{\\\"object\\\":\\\"text\\\",\\\"text\\\":\\\"From the Request Tab -> Exit Procedure\\\",\\\"marks\\\":[]}]}]},{\\\"object\\\":\\\"block\\\",\\\"type\\\":\\\"list-item\\\",\\\"data\\\":{},\\\"nodes\\\":[{\\\"object\\\":\\\"block\\\",\\\"type\\\":\\\"list-item-child\\\",\\\"data\\\":{},\\\"nodes\\\":[{\\\"object\\\":\\\"text\\\",\\\"text\\\":\\\"From the Employee's Profile\\\",\\\"marks\\\":[]}]}]}]},{\\\"object\\\":\\\"block\\\",\\\"type\\\":\\\"image\\\",\\\"data\\\":{\\\"size\\\":63074,\\\"src\\\":\\\"https://onboarding.epam.com/app/cdn/0b3f7bc6-22d4-4170-86b6-b3cadfa4bbb1/image2019-4-2_15-0-4.png?preview=true\\\",\\\"path\\\":\\\"https://onboarding.epam.com/app/cdn/0b3f7bc6-22d4-4170-86b6-b3cadfa4bbb1/image2019-4-2_15-0-4.png?preview=true\\\",\\\"fileName\\\":\\\"image2019-4-2_15-0-4.png\\\",\\\"name\\\":\\\"image2019-4-2_15-0-4.png\\\",\\\"mimeType\\\":{\\\"type\\\":\\\"image\\\",\\\"subtype\\\":\\\"png\\\",\\\"parameters\\\":{},\\\"qualityValue\\\":1,\\\"wildcardType\\\":false,\\\"wildcardSubtype\\\":false,\\\"concrete\\\":true,\\\"charset\\\":null},\\\"type\\\":\\\"image\\\",\\\"id\\\":\\\"0b3f7bc6-22d4-4170-86b6-b3cadfa4bbb1\\\",\\\"imageSize\\\":{\\\"width\\\":707,\\\"height\\\":308},\\\"extension\\\":\\\"png\\\"},\\\"nodes\\\":[{\\\"object\\\":\\\"text\\\",\\\"text\\\":\\\"\\\",\\\"marks\\\":[]}]},{\\\"object\\\":\\\"block\\\",\\\"type\\\":\\\"paragraph\\\",\\\"data\\\":{},\\\"nodes\\\":[{\\\"object\\\":\\\"text\\\",\\\"text\\\":\\\"In either case, the system opens the \\\",\\\"marks\\\":[]},{\\\"object\\\":\\\"text\\\",\\\"text\\\":\\\"Create Exit Request\\\",\\\"marks\\\":[{\\\"object\\\":\\\"mark\\\",\\\"type\\\":\\\"uui-richTextEditor-bold\\\",\\\"data\\\":{}}]},{\\\"object\\\":\\\"text\\\",\\\"text\\\":\\\" form, which covers most of the possible reasons for exiting an Employee.\\\",\\\"marks\\\":[]}]},{\\\"object\\\":\\\"block\\\",\\\"type\\\":\\\"uui-richTextEditor-header-2\\\",\\\"data\\\":{},\\\"nodes\\\":[{\\\"object\\\":\\\"text\\\",\\\"text\\\":\\\"STEP 2. Fill in the following fields in Exit Request:\\\",\\\"marks\\\":[]}]},{\\\"object\\\":\\\"block\\\",\\\"type\\\":\\\"uui-richTextEditor-header-3\\\",\\\"data\\\":{},\\\"nodes\\\":[{\\\"object\\\":\\\"text\\\",\\\"text\\\":\\\"2.1 Exit info:\\\",\\\"marks\\\":[]}]},{\\\"object\\\":\\\"block\\\",\\\"type\\\":\\\"image\\\",\\\"data\\\":{\\\"size\\\":60294,\\\"src\\\":\\\"https://onboarding.epam.com/app/cdn/bebfdb07-66bc-4123-86ba-cecd8dbc4240/image2019-5-27_13-50-52.png?preview=true\\\",\\\"path\\\":\\\"https://onboarding.epam.com/app/cdn/bebfdb07-66bc-4123-86ba-cecd8dbc4240/image2019-5-27_13-50-52.png?preview=true\\\",\\\"fileName\\\":\\\"image2019-5-27_13-50-52.png\\\",\\\"name\\\":\\\"image2019-5-27_13-50-52.png\\\",\\\"mimeType\\\":{\\\"type\\\":\\\"image\\\",\\\"subtype\\\":\\\"png\\\",\\\"parameters\\\":{},\\\"qualityValue\\\":1,\\\"wildcardType\\\":false,\\\"wildcardSubtype\\\":false,\\\"concrete\\\":true,\\\"charset\\\":null},\\\"type\\\":\\\"image\\\",\\\"id\\\":\\\"bebfdb07-66bc-4123-86ba-cecd8dbc4240\\\",\\\"imageSize\\\":{\\\"width\\\":719,\\\"height\\\":453.00000000000006},\\\"extension\\\":\\\"png\\\"},\\\"nodes\\\":[{\\\"object\\\":\\\"text\\\",\\\"text\\\":\\\"\\\",\\\"marks\\\":[]}]},{\\\"object\\\":\\\"block\\\",\\\"type\\\":\\\"image\\\",\\\"data\\\":{\\\"size\\\":20478,\\\"src\\\":\\\"https://onboarding.epam.com/app/cdn/689bcb3c-a927-423b-8223-c52c029afcb8/image2020-5-6_14-17-10.png?preview=true\\\",\\\"path\\\":\\\"https://onboarding.epam.com/app/cdn/689bcb3c-a927-423b-8223-c52c029afcb8/image2020-5-6_14-17-10.png?preview=true\\\",\\\"fileName\\\":\\\"image2020-5-6_14-17-10.png\\\",\\\"name\\\":\\\"image2020-5-6_14-17-10.png\\\",\\\"mimeType\\\":{\\\"type\\\":\\\"image\\\",\\\"subtype\\\":\\\"png\\\",\\\"parameters\\\":{},\\\"qualityValue\\\":1,\\\"wildcardType\\\":false,\\\"wildcardSubtype\\\":false,\\\"concrete\\\":true,\\\"charset\\\":null},\\\"type\\\":\\\"image\\\",\\\"id\\\":\\\"689bcb3c-a927-423b-8223-c52c029afcb8\\\",\\\"imageSize\\\":{\\\"width\\\":666,\\\"height\\\":184},\\\"extension\\\":\\\"png\\\"},\\\"nodes\\\":[{\\\"object\\\":\\\"text\\\",\\\"text\\\":\\\"\\\",\\\"marks\\\":[]}]},{\\\"object\\\":\\\"block\\\",\\\"type\\\":\\\"image\\\",\\\"data\\\":{\\\"size\\\":40388,\\\"src\\\":\\\"https://onboarding.epam.com/app/cdn/bb72e24c-9b5b-40b7-8bc0-5ba2930f45f3/RM.png?preview=true\\\",\\\"path\\\":\\\"https://onboarding.epam.com/app/cdn/bb72e24c-9b5b-40b7-8bc0-5ba2930f45f3/RM.png?preview=true\\\",\\\"align\\\":\\\"align-center\\\",\\\"fileName\\\":\\\"RM.png\\\",\\\"name\\\":\\\"RM.png\\\",\\\"mimeType\\\":{\\\"type\\\":\\\"image\\\",\\\"subtype\\\":\\\"png\\\",\\\"parameters\\\":{},\\\"qualityValue\\\":1,\\\"wildcardType\\\":false,\\\"wildcardSubtype\\\":false,\\\"concrete\\\":true,\\\"charset\\\":null},\\\"type\\\":\\\"image\\\",\\\"id\\\":\\\"bb72e24c-9b5b-40b7-8bc0-5ba2930f45f3\\\",\\\"imageSize\\\":{\\\"width\\\":949,\\\"height\\\":562},\\\"extension\\\":\\\"png\\\"},\\\"nodes\\\":[{\\\"object\\\":\\\"text\\\",\\\"text\\\":\\\"\\\",\\\"marks\\\":[]}]},{\\\"object\\\":\\\"block\\\",\\\"type\\\":\\\"uui-richTextEditor-quote\\\",\\\"data\\\":{},\\\"nodes\\\":[{\\\"object\\\":\\\"block\\\",\\\"type\\\":\\\"paragraph\\\",\\\"data\\\":{},\\\"nodes\\\":[{\\\"object\\\":\\\"text\\\",\\\"text\\\":\\\"Important:\\\",\\\"marks\\\":[{\\\"object\\\":\\\"mark\\\",\\\"type\\\":\\\"uui-richTextEditor-span-mark\\\",\\\"data\\\":{\\\"style\\\":{\\\"color\\\":\\\"rgb(178, 39, 70)\\\"}}},{\\\"object\\\":\\\"mark\\\",\\\"type\\\":\\\"uui-richTextEditor-bold\\\",\\\"data\\\":{}}]},{\\\"object\\\":\\\"text\\\",\\\"text\\\":\\\" the Termination Date of the Employee should not be less than\\\",\\\"marks\\\":[{\\\"object\\\":\\\"mark\\\",\\\"type\\\":\\\"uui-richTextEditor-bold\\\",\\\"data\\\":{}}]},{\\\"object\\\":\\\"text\\\",\\\"text\\\":\\\" \\\",\\\"marks\\\":[{\\\"object\\\":\\\"mark\\\",\\\"type\\\":\\\"uui-richTextEditor-span-mark\\\",\\\"data\\\":{\\\"style\\\":{}}},{\\\"object\\\":\\\"mark\\\",\\\"type\\\":\\\"uui-richTextEditor-bold\\\",\\\"data\\\":{}}]},{\\\"object\\\":\\\"text\\\",\\\"text\\\":\\\"2 weeks\\\",\\\"marks\\\":[{\\\"object\\\":\\\"mark\\\",\\\"type\\\":\\\"uui-richTextEditor-span-mark\\\",\\\"data\\\":{\\\"style\\\":{\\\"color\\\":\\\"rgb(178, 39, 70)\\\"}}},{\\\"object\\\":\\\"mark\\\",\\\"type\\\":\\\"uui-richTextEditor-bold\\\",\\\"data\\\":{}}]},{\\\"object\\\":\\\"text\\\",\\\"text\\\":\\\" \\\",\\\"marks\\\":[{\\\"object\\\":\\\"mark\\\",\\\"type\\\":\\\"uui-richTextEditor-span-mark\\\",\\\"data\\\":{\\\"style\\\":{}}},{\\\"object\\\":\\\"mark\\\",\\\"type\\\":\\\"uui-richTextEditor-bold\\\",\\\"data\\\":{}}]},{\\\"object\\\":\\\"text\\\",\\\"text\\\":\\\"from the date of request submission\\\",\\\"marks\\\":[{\\\"object\\\":\\\"mark\\\",\\\"type\\\":\\\"uui-richTextEditor-bold\\\",\\\"data\\\":{}}]}]},{\\\"object\\\":\\\"block\\\",\\\"type\\\":\\\"paragraph\\\",\\\"data\\\":{},\\\"nodes\\\":[{\\\"object\\\":\\\"text\\\",\\\"text\\\":\\\"This ensures we have adequate time for processing final payments, as well as to transition any work the Employee is engaged in/with our clients\\\",\\\"marks\\\":[{\\\"object\\\":\\\"mark\\\",\\\"type\\\":\\\"uui-richTextEditor-bold\\\",\\\"data\\\":{}}]}]}]},{\\\"object\\\":\\\"block\\\",\\\"type\\\":\\\"uui-richTextEditor-header-3\\\",\\\"data\\\":{},\\\"nodes\\\":[{\\\"object\\\":\\\"text\\\",\\\"text\\\":\\\"2.2 Reasons for leaving:\\\",\\\"marks\\\":[]}]},{\\\"object\\\":\\\"block\\\",\\\"type\\\":\\\"paragraph\\\",\\\"data\\\":{},\\\"nodes\\\":[{\\\"object\\\":\\\"text\\\",\\\"text\\\":\\\"The reasons are grouped into 'Voluntary resignations' and 'Involuntary terminations':\\\",\\\"marks\\\":[]}]},{\\\"object\\\":\\\"block\\\",\\\"type\\\":\\\"image\\\",\\\"data\\\":{\\\"size\\\":288879,\\\"src\\\":\\\"https://onboarding.epam.com/app/cdn/25a916e2-68f0-4f12-ba0e-7e9a5116c61b/Picture1.png?preview=true\\\",\\\"path\\\":\\\"https://onboarding.epam.com/app/cdn/25a916e2-68f0-4f12-ba0e-7e9a5116c61b/Picture1.png?preview=true\\\",\\\"fileName\\\":\\\"Picture1.png\\\",\\\"name\\\":\\\"Picture1.png\\\",\\\"mimeType\\\":{\\\"type\\\":\\\"image\\\",\\\"subtype\\\":\\\"png\\\",\\\"parameters\\\":{},\\\"qualityValue\\\":1,\\\"wildcardType\\\":false,\\\"wildcardSubtype\\\":false,\\\"concrete\\\":true,\\\"charset\\\":null},\\\"type\\\":\\\"image\\\",\\\"id\\\":\\\"25a916e2-68f0-4f12-ba0e-7e9a5116c61b\\\",\\\"imageSize\\\":{\\\"width\\\":680,\\\"height\\\":560},\\\"extension\\\":\\\"png\\\"},\\\"nodes\\\":[{\\\"object\\\":\\\"text\\\",\\\"text\\\":\\\"\\\",\\\"marks\\\":[]}]},{\\\"object\\\":\\\"block\\\",\\\"type\\\":\\\"uui-richTextEditor-quote\\\",\\\"data\\\":{},\\\"nodes\\\":[{\\\"object\\\":\\\"block\\\",\\\"type\\\":\\\"paragraph\\\",\\\"data\\\":{},\\\"nodes\\\":[{\\\"object\\\":\\\"text\\\",\\\"text\\\":\\\"When selecting the reasons for leaving, the usage of “Other” should only be used if \\\",\\\"marks\\\":[{\\\"object\\\":\\\"mark\\\",\\\"type\\\":\\\"uui-richTextEditor-span-mark\\\",\\\"data\\\":{\\\"style\\\":{}}}]},{\\\"object\\\":\\\"text\\\",\\\"text\\\":\\\"there really is no option that describes the situation\\\",\\\"marks\\\":[{\\\"object\\\":\\\"mark\\\",\\\"type\\\":\\\"uui-richTextEditor-bold\\\",\\\"data\\\":{}},{\\\"object\\\":\\\"mark\\\",\\\"type\\\":\\\"uui-richTextEditor-span-mark\\\",\\\"data\\\":{\\\"style\\\":{\\\"color\\\":\\\"rgb(178, 39, 70)\\\"}}}]}]}]},{\\\"object\\\":\\\"block\\\",\\\"type\\\":\\\"uui-richTextEditor-header-2\\\",\\\"data\\\":{},\\\"nodes\\\":[{\\\"object\\\":\\\"text\\\",\\\"text\\\":\\\"STEP 3. Submit Exit Request\\\",\\\"marks\\\":[]}]},{\\\"object\\\":\\\"block\\\",\\\"type\\\":\\\"paragraph\\\",\\\"data\\\":{},\\\"nodes\\\":[{\\\"object\\\":\\\"text\\\",\\\"text\\\":\\\"Click \\\",\\\"marks\\\":[]},{\\\"object\\\":\\\"text\\\",\\\"text\\\":\\\"Save\\\",\\\"marks\\\":[{\\\"object\\\":\\\"mark\\\",\\\"type\\\":\\\"uui-richTextEditor-bold\\\",\\\"data\\\":{}}]},{\\\"object\\\":\\\"text\\\",\\\"text\\\":\\\" \\\",\\\"marks\\\":[]},{\\\"object\\\":\\\"text\\\",\\\"text\\\":\\\"as Draft \\\",\\\"marks\\\":[{\\\"object\\\":\\\"mark\\\",\\\"type\\\":\\\"uui-richTextEditor-bold\\\",\\\"data\\\":{}}]},{\\\"object\\\":\\\"text\\\",\\\"text\\\":\\\"to save the Exit Request in Draft status.\\\",\\\"marks\\\":[]}]},{\\\"object\\\":\\\"block\\\",\\\"type\\\":\\\"paragraph\\\",\\\"data\\\":{},\\\"nodes\\\":[{\\\"object\\\":\\\"text\\\",\\\"text\\\":\\\"To submit the Exit Request, select \\\",\\\"marks\\\":[]},{\\\"object\\\":\\\"text\\\",\\\"text\\\":\\\"Submit\\\",\\\"marks\\\":[{\\\"object\\\":\\\"mark\\\",\\\"type\\\":\\\"uui-richTextEditor-bold\\\",\\\"data\\\":{}}]},{\\\"object\\\":\\\"text\\\",\\\"text\\\":\\\" from the Workflow Action drop-down list and click the Apply button. After you submit the Exit Request, the status will change from \\\",\\\"marks\\\":[]},{\\\"object\\\":\\\"text\\\",\\\"text\\\":\\\"Draft\\\",\\\"marks\\\":[{\\\"object\\\":\\\"mark\\\",\\\"type\\\":\\\"uui-richTextEditor-bold\\\",\\\"data\\\":{}}]},{\\\"object\\\":\\\"text\\\",\\\"text\\\":\\\" to \\\",\\\"marks\\\":[]},{\\\"object\\\":\\\"text\\\",\\\"text\\\":\\\"In Progress\\\",\\\"marks\\\":[{\\\"object\\\":\\\"mark\\\",\\\"type\\\":\\\"uui-richTextEditor-bold\\\",\\\"data\\\":{}}]},{\\\"object\\\":\\\"text\\\",\\\"text\\\":\\\".\\\",\\\"marks\\\":[]}]},{\\\"object\\\":\\\"block\\\",\\\"type\\\":\\\"image\\\",\\\"data\\\":{\\\"size\\\":43678,\\\"src\\\":\\\"https://onboarding.epam.com/app/cdn/9c8848f0-26bb-4d8d-b99d-b23ed65fd239/image2019-4-2_15-4-45.png?preview=true\\\",\\\"path\\\":\\\"https://onboarding.epam.com/app/cdn/9c8848f0-26bb-4d8d-b99d-b23ed65fd239/image2019-4-2_15-4-45.png?preview=true\\\",\\\"fileName\\\":\\\"image2019-4-2_15-4-45.png\\\",\\\"name\\\":\\\"image2019-4-2_15-4-45.png\\\",\\\"mimeType\\\":{\\\"type\\\":\\\"image\\\",\\\"subtype\\\":\\\"png\\\",\\\"parameters\\\":{},\\\"qualityValue\\\":1,\\\"wildcardType\\\":false,\\\"wildcardSubtype\\\":false,\\\"concrete\\\":true,\\\"charset\\\":null},\\\"type\\\":\\\"image\\\",\\\"id\\\":\\\"9c8848f0-26bb-4d8d-b99d-b23ed65fd239\\\",\\\"imageSize\\\":{\\\"width\\\":620,\\\"height\\\":301},\\\"extension\\\":\\\"png\\\"},\\\"nodes\\\":[{\\\"object\\\":\\\"text\\\",\\\"text\\\":\\\"\\\",\\\"marks\\\":[]}]},{\\\"object\\\":\\\"block\\\",\\\"type\\\":\\\"paragraph\\\",\\\"data\\\":{},\\\"nodes\\\":[{\\\"object\\\":\\\"text\\\",\\\"text\\\":\\\"Please note\\\",\\\"marks\\\":[{\\\"object\\\":\\\"mark\\\",\\\"type\\\":\\\"uui-richTextEditor-bold\\\",\\\"data\\\":{}},{\\\"object\\\":\\\"mark\\\",\\\"type\\\":\\\"uui-richTextEditor-underlined\\\",\\\"data\\\":{}},{\\\"object\\\":\\\"mark\\\",\\\"type\\\":\\\"uui-richTextEditor-span-mark\\\",\\\"data\\\":{\\\"style\\\":{\\\"color\\\":\\\"rgb(178, 39, 70)\\\"}}}]},{\\\"object\\\":\\\"text\\\",\\\"text\\\":\\\" \\\",\\\"marks\\\":[{\\\"object\\\":\\\"mark\\\",\\\"type\\\":\\\"uui-richTextEditor-span-mark\\\",\\\"data\\\":{\\\"style\\\":{}}}]},{\\\"object\\\":\\\"text\\\",\\\"text\\\":\\\"that all services/departments responsible for exit procedures will be informed about the termination after Exit Request submission. All following actions will be taken automatically in UPSA. If, for example, the employee has an unused vacation, you will receive a notification with an approval request for a vacation compensation request.\\\",\\\"marks\\\":[]}]},{\\\"object\\\":\\\"block\\\",\\\"type\\\":\\\"uui-richTextEditor-header-2\\\",\\\"data\\\":{},\\\"nodes\\\":[{\\\"object\\\":\\\"text\\\",\\\"text\\\":\\\"STEP 4. Request is Completed\\\",\\\"marks\\\":[]}]},{\\\"object\\\":\\\"block\\\",\\\"type\\\":\\\"paragraph\\\",\\\"data\\\":{},\\\"nodes\\\":[{\\\"object\\\":\\\"text\\\",\\\"text\\\":\\\"After End Date comes, Exit request becomes completed provided all the Responsible services are Approved or Rejected. \\\\r\\\",\\\"marks\\\":[]}]},{\\\"object\\\":\\\"block\\\",\\\"type\\\":\\\"paragraph\\\",\\\"data\\\":{},\\\"nodes\\\":[{\\\"object\\\":\\\"text\\\",\\\"text\\\":\\\"Otherwise Exit Request becomes completed after expiration period of every Exit Checklist item is expired.\\\\r\\\",\\\"marks\\\":[]}]},{\\\"object\\\":\\\"block\\\",\\\"type\\\":\\\"image\\\",\\\"data\\\":{\\\"size\\\":57314,\\\"src\\\":\\\"https://onboarding.epam.com/app/cdn/a7f2b0b6-069a-4259-8b54-b52509cb6268/Picture2.png?preview=true\\\",\\\"path\\\":\\\"https://onboarding.epam.com/app/cdn/a7f2b0b6-069a-4259-8b54-b52509cb6268/Picture2.png?preview=true\\\",\\\"fileName\\\":\\\"Picture2.png\\\",\\\"name\\\":\\\"Picture2.png\\\",\\\"mimeType\\\":{\\\"type\\\":\\\"image\\\",\\\"subtype\\\":\\\"png\\\",\\\"parameters\\\":{},\\\"qualityValue\\\":1,\\\"wildcardType\\\":false,\\\"wildcardSubtype\\\":false,\\\"concrete\\\":true,\\\"charset\\\":null},\\\"type\\\":\\\"image\\\",\\\"id\\\":\\\"a7f2b0b6-069a-4259-8b54-b52509cb6268\\\",\\\"imageSize\\\":{\\\"width\\\":385,\\\"height\\\":282},\\\"extension\\\":\\\"png\\\"},\\\"nodes\\\":[{\\\"object\\\":\\\"text\\\",\\\"text\\\":\\\"\\\",\\\"marks\\\":[]}]},{\\\"object\\\":\\\"block\\\",\\\"type\\\":\\\"paragraph\\\",\\\"data\\\":{},\\\"nodes\\\":[{\\\"object\\\":\\\"text\\\",\\\"text\\\":\\\"\\\",\\\"marks\\\":[]}]},{\\\"object\\\":\\\"block\\\",\\\"type\\\":\\\"uui-richTextEditor-header-2\\\",\\\"data\\\":{},\\\"nodes\\\":[{\\\"object\\\":\\\"text\\\",\\\"text\\\":\\\"How to Edit/Cancel Exit Request\\\\r\\\",\\\"marks\\\":[]}]},{\\\"object\\\":\\\"block\\\",\\\"type\\\":\\\"paragraph\\\",\\\"data\\\":{},\\\"nodes\\\":[{\\\"object\\\":\\\"text\\\",\\\"text\\\":\\\"Exit request can be changed or cancelled manually only before the End date comes. Exit request can be cancelled/changed by:\\\\r\\\",\\\"marks\\\":[]}]},{\\\"object\\\":\\\"block\\\",\\\"type\\\":\\\"paragraph\\\",\\\"data\\\":{},\\\"nodes\\\":[{\\\"object\\\":\\\"text\\\",\\\"text\\\":\\\"\\\\r\\\",\\\"marks\\\":[]}]},{\\\"object\\\":\\\"block\\\",\\\"type\\\":\\\"unordered-list\\\",\\\"data\\\":{},\\\"nodes\\\":[{\\\"object\\\":\\\"block\\\",\\\"type\\\":\\\"list-item\\\",\\\"data\\\":{},\\\"nodes\\\":[{\\\"object\\\":\\\"block\\\",\\\"type\\\":\\\"list-item-child\\\",\\\"data\\\":{},\\\"nodes\\\":[{\\\"object\\\":\\\"text\\\",\\\"text\\\":\\\"Employee`s Direct Resource Manager\\\\r\\\",\\\"marks\\\":[]}]}]},{\\\"object\\\":\\\"block\\\",\\\"type\\\":\\\"list-item\\\",\\\"data\\\":{},\\\"nodes\\\":[{\\\"object\\\":\\\"block\\\",\\\"type\\\":\\\"list-item-child\\\",\\\"data\\\":{},\\\"nodes\\\":[{\\\"object\\\":\\\"text\\\",\\\"text\\\":\\\"Employee`s Resource Manager by Hierarchy\\\\r\\\",\\\"marks\\\":[]}]}]},{\\\"object\\\":\\\"block\\\",\\\"type\\\":\\\"list-item\\\",\\\"data\\\":{},\\\"nodes\\\":[{\\\"object\\\":\\\"block\\\",\\\"type\\\":\\\"list-item-child\\\",\\\"data\\\":{},\\\"nodes\\\":[{\\\"object\\\":\\\"text\\\",\\\"text\\\":\\\"Senior Management of the Company\\\\r\\\",\\\"marks\\\":[]}]}]},{\\\"object\\\":\\\"block\\\",\\\"type\\\":\\\"list-item\\\",\\\"data\\\":{},\\\"nodes\\\":[{\\\"object\\\":\\\"block\\\",\\\"type\\\":\\\"list-item-child\\\",\\\"data\\\":{},\\\"nodes\\\":[{\\\"object\\\":\\\"text\\\",\\\"text\\\":\\\"EPAM Support Team\\\\r\\\",\\\"marks\\\":[]}]}]}]},{\\\"object\\\":\\\"block\\\",\\\"type\\\":\\\"paragraph\\\",\\\"data\\\":{},\\\"nodes\\\":[{\\\"object\\\":\\\"text\\\",\\\"text\\\":\\\"When the End date \\\",\\\"marks\\\":[]},{\\\"object\\\":\\\"text\\\",\\\"text\\\":\\\"has come\\\",\\\"marks\\\":[{\\\"object\\\":\\\"mark\\\",\\\"type\\\":\\\"uui-richTextEditor-underlined\\\",\\\"data\\\":{}}]},{\\\"object\\\":\\\"text\\\",\\\"text\\\":\\\", Exit Request can still be changed or cancelled by Support Team while Exit Request status is \\\",\\\"marks\\\":[]},{\\\"object\\\":\\\"text\\\",\\\"text\\\":\\\"\\\\\\\"In Progress\\\\\\\"\\\",\\\"marks\\\":[{\\\"object\\\":\\\"mark\\\",\\\"type\\\":\\\"uui-richTextEditor-bold\\\",\\\"data\\\":{}}]},{\\\"object\\\":\\\"text\\\",\\\"text\\\":\\\". \\\",\\\"marks\\\":[]}]},{\\\"object\\\":\\\"block\\\",\\\"type\\\":\\\"paragraph\\\",\\\"data\\\":{},\\\"nodes\\\":[{\\\"object\\\":\\\"text\\\",\\\"text\\\":\\\"\\\",\\\"marks\\\":[]}]},{\\\"object\\\":\\\"block\\\",\\\"type\\\":\\\"paragraph\\\",\\\"data\\\":{},\\\"nodes\\\":[{\\\"object\\\":\\\"block\\\",\\\"type\\\":\\\"table\\\",\\\"data\\\":{\\\"cellSizes\\\":[230,259]},\\\"nodes\\\":[{\\\"object\\\":\\\"block\\\",\\\"type\\\":\\\"table_row\\\",\\\"data\\\":{},\\\"nodes\\\":[{\\\"object\\\":\\\"block\\\",\\\"type\\\":\\\"table_header_cell\\\",\\\"data\\\":{},\\\"nodes\\\":[{\\\"object\\\":\\\"block\\\",\\\"type\\\":\\\"paragraph\\\",\\\"data\\\":{},\\\"nodes\\\":[{\\\"object\\\":\\\"text\\\",\\\"text\\\":\\\"Item that should be changed\\\",\\\"marks\\\":[]}]}]},{\\\"object\\\":\\\"block\\\",\\\"type\\\":\\\"table_header_cell\\\",\\\"data\\\":{},\\\"nodes\\\":[{\\\"object\\\":\\\"block\\\",\\\"type\\\":\\\"paragraph\\\",\\\"data\\\":{},\\\"nodes\\\":[{\\\"object\\\":\\\"text\\\",\\\"text\\\":\\\"Help resource\\\",\\\"marks\\\":[]}]}]}]},{\\\"object\\\":\\\"block\\\",\\\"type\\\":\\\"table_row\\\",\\\"data\\\":{},\\\"nodes\\\":[{\\\"object\\\":\\\"block\\\",\\\"type\\\":\\\"table_cell\\\",\\\"data\\\":{},\\\"nodes\\\":[{\\\"object\\\":\\\"block\\\",\\\"type\\\":\\\"paragraph\\\",\\\"data\\\":{},\\\"nodes\\\":[{\\\"object\\\":\\\"text\\\",\\\"text\\\":\\\"End date\\\",\\\"marks\\\":[]}]}]},{\\\"object\\\":\\\"block\\\",\\\"type\\\":\\\"table_cell\\\",\\\"data\\\":{},\\\"nodes\\\":[{\\\"object\\\":\\\"block\\\",\\\"type\\\":\\\"paragraph\\\",\\\"data\\\":{},\\\"nodes\\\":[{\\\"object\\\":\\\"text\\\",\\\"text\\\":\\\"Submit request to support using \\\",\\\"marks\\\":[]},{\\\"object\\\":\\\"inline\\\",\\\"type\\\":\\\"link\\\",\\\"data\\\":{\\\"url\\\":\\\"https://support.epam.com/esp/ess.do#orderitem/caChangEndER\\\"},\\\"nodes\\\":[{\\\"object\\\":\\\"text\\\",\\\"text\\\":\\\"this template\\\",\\\"marks\\\":[]}]},{\\\"object\\\":\\\"text\\\",\\\"text\\\":\\\"\\\",\\\"marks\\\":[]}]}]}]},{\\\"object\\\":\\\"block\\\",\\\"type\\\":\\\"table_row\\\",\\\"data\\\":{},\\\"nodes\\\":[{\\\"object\\\":\\\"block\\\",\\\"type\\\":\\\"table_cell\\\",\\\"data\\\":{},\\\"nodes\\\":[{\\\"object\\\":\\\"block\\\",\\\"type\\\":\\\"paragraph\\\",\\\"data\\\":{},\\\"nodes\\\":[{\\\"object\\\":\\\"text\\\",\\\"text\\\":\\\"Termination Type\\\",\\\"marks\\\":[]}]}]},{\\\"object\\\":\\\"block\\\",\\\"type\\\":\\\"table_cell\\\",\\\"data\\\":{\\\"colSpan\\\":1,\\\"rowSpan\\\":3},\\\"nodes\\\":[{\\\"object\\\":\\\"block\\\",\\\"type\\\":\\\"paragraph\\\",\\\"data\\\":{},\\\"nodes\\\":[{\\\"object\\\":\\\"text\\\",\\\"text\\\":\\\"Send request to\\\",\\\"marks\\\":[]},{\\\"object\\\":\\\"inline\\\",\\\"type\\\":\\\"link\\\",\\\"data\\\":{\\\"url\\\":\\\"mailto:Support@epam.com\\\"},\\\"nodes\\\":[{\\\"object\\\":\\\"text\\\",\\\"text\\\":\\\" WFT Support EPAM\\\",\\\"marks\\\":[]}]},{\\\"object\\\":\\\"text\\\",\\\"text\\\":\\\"\\\",\\\"marks\\\":[]}]}]}]},{\\\"object\\\":\\\"block\\\",\\\"type\\\":\\\"table_row\\\",\\\"data\\\":{},\\\"nodes\\\":[{\\\"object\\\":\\\"block\\\",\\\"type\\\":\\\"table_cell\\\",\\\"data\\\":{},\\\"nodes\\\":[{\\\"object\\\":\\\"block\\\",\\\"type\\\":\\\"paragraph\\\",\\\"data\\\":{},\\\"nodes\\\":[{\\\"object\\\":\\\"text\\\",\\\"text\\\":\\\"Settlement/Severance Agreement checkbox\\\",\\\"marks\\\":[]}]}]},{\\\"object\\\":\\\"block\\\",\\\"type\\\":\\\"table_cell\\\",\\\"data\\\":{\\\"style\\\":\\\"none\\\"},\\\"nodes\\\":[{\\\"object\\\":\\\"block\\\",\\\"type\\\":\\\"paragraph\\\",\\\"data\\\":{},\\\"nodes\\\":[{\\\"object\\\":\\\"text\\\",\\\"text\\\":\\\"\\\",\\\"marks\\\":[]}]}]}]},{\\\"object\\\":\\\"block\\\",\\\"type\\\":\\\"table_row\\\",\\\"data\\\":{},\\\"nodes\\\":[{\\\"object\\\":\\\"block\\\",\\\"type\\\":\\\"table_cell\\\",\\\"data\\\":{},\\\"nodes\\\":[{\\\"object\\\":\\\"block\\\",\\\"type\\\":\\\"paragraph\\\",\\\"data\\\":{},\\\"nodes\\\":[{\\\"object\\\":\\\"text\\\",\\\"text\\\":\\\"Reasons for leaving\\\",\\\"marks\\\":[]}]}]},{\\\"object\\\":\\\"block\\\",\\\"type\\\":\\\"table_cell\\\",\\\"data\\\":{\\\"style\\\":\\\"none\\\"},\\\"nodes\\\":[{\\\"object\\\":\\\"block\\\",\\\"type\\\":\\\"paragraph\\\",\\\"data\\\":{},\\\"nodes\\\":[{\\\"object\\\":\\\"text\\\",\\\"text\\\":\\\"\\\",\\\"marks\\\":[]}]}]}]}]}]},{\\\"object\\\":\\\"block\\\",\\\"type\\\":\\\"paragraph\\\",\\\"data\\\":{},\\\"nodes\\\":[{\\\"object\\\":\\\"text\\\",\\\"text\\\":\\\"\\\",\\\"marks\\\":[]}]},{\\\"object\\\":\\\"block\\\",\\\"type\\\":\\\"paragraph\\\",\\\"data\\\":{},\\\"nodes\\\":[{\\\"object\\\":\\\"text\\\",\\\"text\\\":\\\"If the Exit request is completed, it will be more complicated to change the End date. When End date comes, all EPAM systems are notified about that and do not recheck this data, so all the systems should be notified again. It requires additional work and time for services. Such cases are treated as exceptional.\\\",\\\"marks\\\":[]}]},{\\\"object\\\":\\\"block\\\",\\\"type\\\":\\\"paragraph\\\",\\\"data\\\":{},\\\"nodes\\\":[{\\\"object\\\":\\\"text\\\",\\\"text\\\":\\\"More info on UPSA Exit Request functionality is available \\\",\\\"marks\\\":[]},{\\\"object\\\":\\\"inline\\\",\\\"type\\\":\\\"link\\\",\\\"data\\\":{\\\"url\\\":\\\"https://kb.epam.com/display/UPSA/Creating+an+exit+request\\\"},\\\"nodes\\\":[{\\\"object\\\":\\\"text\\\",\\\"text\\\":\\\"here\\\",\\\"marks\\\":[]}]},{\\\"object\\\":\\\"text\\\",\\\"text\\\":\\\".\\\",\\\"marks\\\":[]}]},{\\\"object\\\":\\\"block\\\",\\\"type\\\":\\\"note-link\\\",\\\"data\\\":{},\\\"nodes\\\":[{\\\"object\\\":\\\"text\\\",\\\"text\\\":\\\"This \\\",\\\"marks\\\":[{\\\"object\\\":\\\"mark\\\",\\\"type\\\":\\\"uui-richTextEditor-bold\\\",\\\"data\\\":{}}]},{\\\"object\\\":\\\"inline\\\",\\\"type\\\":\\\"link\\\",\\\"data\\\":{\\\"url\\\":\\\"https://learn.epam.com/detailsPage?id=827edc47-cd76-4366-bbfe-cbdc7f2a98a3\\\"},\\\"nodes\\\":[{\\\"object\\\":\\\"text\\\",\\\"text\\\":\\\"training\\\",\\\"marks\\\":[{\\\"object\\\":\\\"mark\\\",\\\"type\\\":\\\"uui-richTextEditor-bold\\\",\\\"data\\\":{}}]}]},{\\\"object\\\":\\\"text\\\",\\\"text\\\":\\\" will help you learn more about Exit Process at EPAM.\\\",\\\"marks\\\":[{\\\"object\\\":\\\"mark\\\",\\\"type\\\":\\\"uui-richTextEditor-bold\\\",\\\"data\\\":{}}]}]},{\\\"object\\\":\\\"block\\\",\\\"type\\\":\\\"paragraph\\\",\\\"data\\\":{},\\\"nodes\\\":[{\\\"object\\\":\\\"text\\\",\\\"text\\\":\\\"Please address any questions to your Manager, People Partner or \\\",\\\"marks\\\":[]},{\\\"object\\\":\\\"inline\\\",\\\"type\\\":\\\"link\\\",\\\"data\\\":{\\\"url\\\":\\\"mailto:OrgExitManagement@epam.com\\\"},\\\"nodes\\\":[{\\\"object\\\":\\\"text\\\",\\\"text\\\":\\\"Org Exit Management\\\",\\\"marks\\\":[]}]},{\\\"object\\\":\\\"text\\\",\\\"text\\\":\\\".\\\",\\\"marks\\\":[]}]}]}}\""}